{
"meta":{"test_sets":[],"test_metrics":[],"learn_metrics":[{"best_value":"Min","name":"RMSE"}],"launch_mode":"Train","parameters":"","iteration_count":1000,"learn_sets":["learn"],"name":"experiment"},
"iterations":[
{"learn":[14.59871775],"iteration":0,"passed_time":0.003655320039,"remaining_time":3.651664719},
{"learn":[14.22518863],"iteration":1,"passed_time":0.006734566311,"remaining_time":3.360548589},
{"learn":[13.8866124],"iteration":2,"passed_time":0.009368086374,"remaining_time":3.113327372},
{"learn":[13.52356875],"iteration":3,"passed_time":0.01298694245,"remaining_time":3.23374867},
{"learn":[13.18870211],"iteration":4,"passed_time":0.01584007171,"remaining_time":3.15217427},
{"learn":[12.9124226],"iteration":5,"passed_time":0.01847686179,"remaining_time":3.061000103},
{"learn":[12.60003351],"iteration":6,"passed_time":0.02061749284,"remaining_time":2.924738626},
{"learn":[12.32990573],"iteration":7,"passed_time":0.02316997014,"remaining_time":2.873076297},
{"learn":[12.0660619],"iteration":8,"passed_time":0.02591402596,"remaining_time":2.853422192},
{"learn":[11.77309809],"iteration":9,"passed_time":0.02813411387,"remaining_time":2.785277273},
{"learn":[11.49227636],"iteration":10,"passed_time":0.0303100819,"remaining_time":2.725151909},
{"learn":[11.26264833],"iteration":11,"passed_time":0.03267027356,"remaining_time":2.689852523},
{"learn":[11.04260393],"iteration":12,"passed_time":0.03495352053,"remaining_time":2.653778828},
{"learn":[10.79916926],"iteration":13,"passed_time":0.03808648655,"remaining_time":2.682376838},
{"learn":[10.5541002],"iteration":14,"passed_time":0.04090581507,"remaining_time":2.686148523},
{"learn":[10.31918115],"iteration":15,"passed_time":0.04350618291,"remaining_time":2.675630249},
{"learn":[10.10004441],"iteration":16,"passed_time":0.04558103074,"remaining_time":2.635656072},
{"learn":[9.894556723],"iteration":17,"passed_time":0.0476773914,"remaining_time":2.601066575},
{"learn":[9.690174082],"iteration":18,"passed_time":0.04996540821,"remaining_time":2.579792919},
{"learn":[9.506034866],"iteration":19,"passed_time":0.05242811214,"remaining_time":2.568977495},
{"learn":[9.338524633],"iteration":20,"passed_time":0.05563025285,"remaining_time":2.593429407},
{"learn":[9.170203312],"iteration":21,"passed_time":0.05896456571,"remaining_time":2.621242967},
{"learn":[9.010299969],"iteration":22,"passed_time":0.06132147837,"remaining_time":2.604829755},
{"learn":[8.843866678],"iteration":23,"passed_time":0.06347732144,"remaining_time":2.581411072},
{"learn":[8.690548059],"iteration":24,"passed_time":0.06582131774,"remaining_time":2.567031392},
{"learn":[8.555307687],"iteration":25,"passed_time":0.06807058918,"remaining_time":2.550028995},
{"learn":[8.413851302],"iteration":26,"passed_time":0.07085951003,"remaining_time":2.553566787},
{"learn":[8.29256019],"iteration":27,"passed_time":0.07368656893,"remaining_time":2.557976607},
{"learn":[8.162193833],"iteration":28,"passed_time":0.07556650169,"remaining_time":2.530174936},
{"learn":[8.040736294],"iteration":29,"passed_time":0.07742630367,"remaining_time":2.503450485},
{"learn":[7.921220278],"iteration":30,"passed_time":0.07927620636,"remaining_time":2.478020773},
{"learn":[7.809589039],"iteration":31,"passed_time":0.08109136669,"remaining_time":2.453013842},
{"learn":[7.699675801],"iteration":32,"passed_time":0.08396275988,"remaining_time":2.460363297},
{"learn":[7.60645267],"iteration":33,"passed_time":0.08745560096,"remaining_time":2.484767957},
{"learn":[7.498880302],"iteration":34,"passed_time":0.09005525217,"remaining_time":2.482951953},
{"learn":[7.401158744],"iteration":35,"passed_time":0.09199032262,"remaining_time":2.463296417},
{"learn":[7.306431077],"iteration":36,"passed_time":0.09411805157,"remaining_time":2.449613072},
{"learn":[7.223863468],"iteration":37,"passed_time":0.09598476749,"remaining_time":2.429930166},
{"learn":[7.143477682],"iteration":38,"passed_time":0.09824257889,"remaining_time":2.420797905},
{"learn":[7.062817131],"iteration":39,"passed_time":0.1019592323,"remaining_time":2.447021576},
{"learn":[6.990793435],"iteration":40,"passed_time":0.104354217,"remaining_time":2.440870589},
{"learn":[6.931862224],"iteration":41,"passed_time":0.1066250266,"remaining_time":2.432066084},
{"learn":[6.858296558],"iteration":42,"passed_time":0.1086845119,"remaining_time":2.418862278},
{"learn":[6.786268161],"iteration":43,"passed_time":0.1107012869,"remaining_time":2.405237051},
{"learn":[6.717118549],"iteration":44,"passed_time":0.1136069857,"remaining_time":2.410992696},
{"learn":[6.652948106],"iteration":45,"passed_time":0.1176728681,"remaining_time":2.440432961},
{"learn":[6.589686076],"iteration":46,"passed_time":0.1199738842,"remaining_time":2.43266195},
{"learn":[6.531283097],"iteration":47,"passed_time":0.1224594682,"remaining_time":2.428779453},
{"learn":[6.471368031],"iteration":48,"passed_time":0.1244568491,"remaining_time":2.415478847},
{"learn":[6.416481395],"iteration":49,"passed_time":0.1267870878,"remaining_time":2.408954668},
{"learn":[6.369870822],"iteration":50,"passed_time":0.1296306182,"remaining_time":2.41214621},
{"learn":[6.325678067],"iteration":51,"passed_time":0.132516942,"remaining_time":2.415885788},
{"learn":[6.275766122],"iteration":52,"passed_time":0.1344390195,"remaining_time":2.402146254},
{"learn":[6.224773967],"iteration":53,"passed_time":0.1367019112,"remaining_time":2.394814964},
{"learn":[6.182249254],"iteration":54,"passed_time":0.1389949123,"remaining_time":2.388185311},
{"learn":[6.139904173],"iteration":55,"passed_time":0.1409626924,"remaining_time":2.376228244},
{"learn":[6.100525536],"iteration":56,"passed_time":0.1435118807,"remaining_time":2.374240412},
{"learn":[6.062568564],"iteration":57,"passed_time":0.1462209148,"remaining_time":2.374829341},
{"learn":[6.030559288],"iteration":58,"passed_time":0.148538441,"remaining_time":2.369062254},
{"learn":[5.997931376],"iteration":59,"passed_time":0.15056202,"remaining_time":2.35880498},
{"learn":[5.964103835],"iteration":60,"passed_time":0.1526611965,"remaining_time":2.349981369},
{"learn":[5.933729724],"iteration":61,"passed_time":0.1548322706,"remaining_time":2.342462417},
{"learn":[5.901932711],"iteration":62,"passed_time":0.1576877019,"remaining_time":2.345291693},
{"learn":[5.873727795],"iteration":63,"passed_time":0.1607715083,"remaining_time":2.351283309},
{"learn":[5.846485734],"iteration":64,"passed_time":0.1631862853,"remaining_time":2.34737195},
{"learn":[5.820630862],"iteration":65,"passed_time":0.1651621079,"remaining_time":2.337294072},
{"learn":[5.793646238],"iteration":66,"passed_time":0.1672791993,"remaining_time":2.329425267},
{"learn":[5.765388646],"iteration":67,"passed_time":0.1695345328,"remaining_time":2.323620361},
{"learn":[5.747073912],"iteration":68,"passed_time":0.1721007345,"remaining_time":2.322112808},
{"learn":[5.722315217],"iteration":69,"passed_time":0.1744448232,"remaining_time":2.317624079},
{"learn":[5.699970599],"iteration":70,"passed_time":0.1769932383,"remaining_time":2.315869273},
{"learn":[5.682732647],"iteration":71,"passed_time":0.1789956525,"remaining_time":2.307055077},
{"learn":[5.663525791],"iteration":72,"passed_time":0.1811478036,"remaining_time":2.300328958},
{"learn":[5.642381613],"iteration":73,"passed_time":0.1830886959,"remaining_time":2.29108287},
{"learn":[5.621404779],"iteration":74,"passed_time":0.1857612486,"remaining_time":2.2910554},
{"learn":[5.602460129],"iteration":75,"passed_time":0.1883832085,"remaining_time":2.290343219},
{"learn":[5.587337574],"iteration":76,"passed_time":0.1910688407,"remaining_time":2.290344675},
{"learn":[5.572393026],"iteration":77,"passed_time":0.1937406721,"remaining_time":2.290114098},
{"learn":[5.558425806],"iteration":78,"passed_time":0.1957375977,"remaining_time":2.281953513},
{"learn":[5.541518902],"iteration":79,"passed_time":0.1977935115,"remaining_time":2.274625382},
{"learn":[5.526157283],"iteration":80,"passed_time":0.2006595132,"remaining_time":2.276618428},
{"learn":[5.511746977],"iteration":81,"passed_time":0.2031299211,"remaining_time":2.274064239},
{"learn":[5.504975022],"iteration":82,"passed_time":0.2048789592,"remaining_time":2.263542236},
{"learn":[5.493980522],"iteration":83,"passed_time":0.2076468241,"remaining_time":2.264339177},
{"learn":[5.480745463],"iteration":84,"passed_time":0.2096474786,"remaining_time":2.256793447},
{"learn":[5.464052013],"iteration":85,"passed_time":0.2115189776,"remaining_time":2.248004018},
{"learn":[5.449143727],"iteration":86,"passed_time":0.2137200131,"remaining_time":2.242831862},
{"learn":[5.438255432],"iteration":87,"passed_time":0.215622311,"remaining_time":2.234631224},
{"learn":[5.425927931],"iteration":88,"passed_time":0.2181887371,"remaining_time":2.233370107},
{"learn":[5.412331217],"iteration":89,"passed_time":0.2210152685,"remaining_time":2.234709937},
{"learn":[5.400691499],"iteration":90,"passed_time":0.2232071953,"remaining_time":2.229619126},
{"learn":[5.391618744],"iteration":91,"passed_time":0.225291408,"remaining_time":2.223528244},
{"learn":[5.380766572],"iteration":92,"passed_time":0.2274892279,"remaining_time":2.218631502},
{"learn":[5.372207183],"iteration":93,"passed_time":0.2295061655,"remaining_time":2.212048786},
{"learn":[5.362918837],"iteration":94,"passed_time":0.2319306669,"remaining_time":2.209444774},
{"learn":[5.348292324],"iteration":95,"passed_time":0.2344155538,"remaining_time":2.207413132},
{"learn":[5.339772295],"iteration":96,"passed_time":0.2369087848,"remaining_time":2.205449821},
{"learn":[5.331515983],"iteration":97,"passed_time":0.2388204613,"remaining_time":2.198123022},
{"learn":[5.323861644],"iteration":98,"passed_time":0.2410528345,"remaining_time":2.193824282},
{"learn":[5.313277281],"iteration":99,"passed_time":0.2431752798,"remaining_time":2.188577518},
{"learn":[5.30685627],"iteration":100,"passed_time":0.2452538022,"remaining_time":2.183001665},
{"learn":[5.29652059],"iteration":101,"passed_time":0.2485549469,"remaining_time":2.188258258},
{"learn":[5.288350766],"iteration":102,"passed_time":0.2512560004,"remaining_time":2.188122644},
{"learn":[5.27993346],"iteration":103,"passed_time":0.2535679175,"remaining_time":2.184585136},
{"learn":[5.271789139],"iteration":104,"passed_time":0.2557938484,"remaining_time":2.180338041},
{"learn":[5.262684686],"iteration":105,"passed_time":0.258046627,"remaining_time":2.176355514},
{"learn":[5.251619772],"iteration":106,"passed_time":0.2601078925,"remaining_time":2.170806991},
{"learn":[5.241012171],"iteration":107,"passed_time":0.2638639066,"remaining_time":2.179320413},
{"learn":[5.232684032],"iteration":108,"passed_time":0.2664227385,"remaining_time":2.177822569},
{"learn":[5.224267141],"iteration":109,"passed_time":0.2691530172,"remaining_time":2.177692594},
{"learn":[5.216324968],"iteration":110,"passed_time":0.2713287423,"remaining_time":2.173074341},
{"learn":[5.211102527],"iteration":111,"passed_time":0.2732747281,"remaining_time":2.166678202},
{"learn":[5.206364257],"iteration":112,"passed_time":0.2751120984,"remaining_time":2.159508241},
{"learn":[5.196937641],"iteration":113,"passed_time":0.2772048241,"remaining_time":2.15441644},
{"learn":[5.190746047],"iteration":114,"passed_time":0.2802493851,"remaining_time":2.156701789},
{"learn":[5.181885213],"iteration":115,"passed_time":0.2834855251,"remaining_time":2.160355208},
{"learn":[5.178293568],"iteration":116,"passed_time":0.2852130878,"remaining_time":2.152505612},
{"learn":[5.170991438],"iteration":117,"passed_time":0.2871377615,"remaining_time":2.146233099},
{"learn":[5.166257212],"iteration":118,"passed_time":0.2890959772,"remaining_time":2.140281982},
{"learn":[5.161421246],"iteration":119,"passed_time":0.2907487209,"remaining_time":2.132157286},
{"learn":[5.158223542],"iteration":120,"passed_time":0.2929913709,"remaining_time":2.128424918},
{"learn":[5.15470988],"iteration":121,"passed_time":0.2951219342,"remaining_time":2.123910314},
{"learn":[5.146388143],"iteration":122,"passed_time":0.2981316794,"remaining_time":2.125703113},
{"learn":[5.139529364],"iteration":123,"passed_time":0.3005551759,"remaining_time":2.123276888},
{"learn":[5.134276023],"iteration":124,"passed_time":0.3025894702,"remaining_time":2.118126291},
{"learn":[5.128536065],"iteration":125,"passed_time":0.3046810937,"remaining_time":2.113422825},
{"learn":[5.123300353],"iteration":126,"passed_time":0.3074423689,"remaining_time":2.113363685},
{"learn":[5.116200518],"iteration":127,"passed_time":0.3106265213,"remaining_time":2.116143177},
{"learn":[5.108728704],"iteration":128,"passed_time":0.3126935379,"remaining_time":2.111287376},
{"learn":[5.104075866],"iteration":129,"passed_time":0.314692474,"remaining_time":2.106018865},
{"learn":[5.100317606],"iteration":130,"passed_time":0.3167701467,"remaining_time":2.101322576},
{"learn":[5.095814182],"iteration":131,"passed_time":0.318874647,"remaining_time":2.096842376},
{"learn":[5.092146915],"iteration":132,"passed_time":0.3212957221,"remaining_time":2.094461587},
{"learn":[5.085258329],"iteration":133,"passed_time":0.3247944975,"remaining_time":2.099045036},
{"learn":[5.079219421],"iteration":134,"passed_time":0.3274330742,"remaining_time":2.097997105},
{"learn":[5.076476829],"iteration":135,"passed_time":0.3296311634,"remaining_time":2.094127391},
{"learn":[5.072133867],"iteration":136,"passed_time":0.3320191497,"remaining_time":2.091478293},
{"learn":[5.067031564],"iteration":137,"passed_time":0.334185332,"remaining_time":2.087447508},
{"learn":[5.061358312],"iteration":138,"passed_time":0.3363734865,"remaining_time":2.083579654},
{"learn":[5.056759124],"iteration":139,"passed_time":0.3396357132,"remaining_time":2.086333667},
{"learn":[5.050254],"iteration":140,"passed_time":0.3414929349,"remaining_time":2.080442774},
{"learn":[5.048376474],"iteration":141,"passed_time":0.3429107586,"remaining_time":2.071953739},
{"learn":[5.042603751],"iteration":142,"passed_time":0.3449593074,"remaining_time":2.067343542},
{"learn":[5.037477349],"iteration":143,"passed_time":0.3469972926,"remaining_time":2.062706128},
{"learn":[5.03230489],"iteration":144,"passed_time":0.348911992,"remaining_time":2.057377608},
{"learn":[5.025976187],"iteration":145,"passed_time":0.350970306,"remaining_time":2.052935899},
{"learn":[5.01952451],"iteration":146,"passed_time":0.3535560068,"remaining_time":2.051586897},
{"learn":[5.017569424],"iteration":147,"passed_time":0.3557130888,"remaining_time":2.047753727},
{"learn":[5.008962367],"iteration":148,"passed_time":0.3576346905,"remaining_time":2.042598132},
{"learn":[5.003880266],"iteration":149,"passed_time":0.3597334044,"remaining_time":2.038489291},
{"learn":[4.996387564],"iteration":150,"passed_time":0.3616747397,"remaining_time":2.033522212},
{"learn":[4.993361683],"iteration":151,"passed_time":0.3635016715,"remaining_time":2.027956694},
{"learn":[4.99005752],"iteration":152,"passed_time":0.3656453001,"remaining_time":2.024193262},
{"learn":[4.986908764],"iteration":153,"passed_time":0.3679810094,"remaining_time":2.021506064},
{"learn":[4.985207175],"iteration":154,"passed_time":0.3705346844,"remaining_time":2.020011667},
{"learn":[4.979003494],"iteration":155,"passed_time":0.3726349282,"remaining_time":2.016050509},
{"learn":[4.973142217],"iteration":156,"passed_time":0.3744141875,"remaining_time":2.010389555},
{"learn":[4.967056696],"iteration":157,"passed_time":0.3763859485,"remaining_time":2.005803599},
{"learn":[4.961460696],"iteration":158,"passed_time":0.3784756487,"remaining_time":2.001874343},
{"learn":[4.954240363],"iteration":159,"passed_time":0.3803158306,"remaining_time":1.996658111},
{"learn":[4.952320707],"iteration":160,"passed_time":0.3816246812,"remaining_time":1.988714954},
{"learn":[4.948337777],"iteration":161,"passed_time":0.3842314925,"remaining_time":1.987567844},
{"learn":[4.943228639],"iteration":162,"passed_time":0.3860982416,"remaining_time":1.982602627},
{"learn":[4.938545759],"iteration":163,"passed_time":0.3883374205,"remaining_time":1.97957368},
{"learn":[4.935330572],"iteration":164,"passed_time":0.3902435335,"remaining_time":1.974868791},
{"learn":[4.932051543],"iteration":165,"passed_time":0.3920750592,"remaining_time":1.969822888},
{"learn":[4.928964153],"iteration":166,"passed_time":0.3944626299,"remaining_time":1.967589046},
{"learn":[4.922860227],"iteration":167,"passed_time":0.3975480977,"remaining_time":1.968809627},
{"learn":[4.917668772],"iteration":168,"passed_time":0.4002209319,"remaining_time":1.967950263},
{"learn":[4.910365386],"iteration":169,"passed_time":0.4025025634,"remaining_time":1.965159574},
{"learn":[4.906457206],"iteration":170,"passed_time":0.4046330385,"remaining_time":1.96164204},
{"learn":[4.901996508],"iteration":171,"passed_time":0.4069656679,"remaining_time":1.959113797},
{"learn":[4.896816173],"iteration":172,"passed_time":0.4088838375,"remaining_time":1.954606553},
{"learn":[4.891123132],"iteration":173,"passed_time":0.4108040703,"remaining_time":1.950138863},
{"learn":[4.887630202],"iteration":174,"passed_time":0.4148146361,"remaining_time":1.955554713},
{"learn":[4.885259712],"iteration":175,"passed_time":0.4178170232,"remaining_time":1.956143336},
{"learn":[4.880659728],"iteration":176,"passed_time":0.4199620634,"remaining_time":1.952704962},
{"learn":[4.877299723],"iteration":177,"passed_time":0.4224779674,"remaining_time":1.95099376},
{"learn":[4.874038772],"iteration":178,"passed_time":0.4249344255,"remaining_time":1.949000912},
{"learn":[4.86943698],"iteration":179,"passed_time":0.4273964281,"remaining_time":1.947028172},
{"learn":[4.861268711],"iteration":180,"passed_time":0.4304899464,"remaining_time":1.947907547},
{"learn":[4.858673056],"iteration":181,"passed_time":0.432992802,"remaining_time":1.946088528},
{"learn":[4.854036207],"iteration":182,"passed_time":0.4347832883,"remaining_time":1.941081675},
{"learn":[4.85130244],"iteration":183,"passed_time":0.4382501097,"remaining_time":1.943543965},
{"learn":[4.847510084],"iteration":184,"passed_time":0.4404470825,"remaining_time":1.940347958},
{"learn":[4.845691673],"iteration":185,"passed_time":0.4433747916,"remaining_time":1.940360647},
{"learn":[4.842058646],"iteration":186,"passed_time":0.4459831819,"remaining_time":1.93895362},
{"learn":[4.838623675],"iteration":187,"passed_time":0.44856715,"remaining_time":1.937428329},
{"learn":[4.834602161],"iteration":188,"passed_time":0.4510137848,"remaining_time":1.935302537},
{"learn":[4.830858976],"iteration":189,"passed_time":0.4531759171,"remaining_time":1.931960489},
{"learn":[4.827590511],"iteration":190,"passed_time":0.4554915484,"remaining_time":1.929280956},
{"learn":[4.822246226],"iteration":191,"passed_time":0.4575193765,"remaining_time":1.925394043},
{"learn":[4.816686395],"iteration":192,"passed_time":0.4602752159,"remaining_time":1.924570462},
{"learn":[4.814797121],"iteration":193,"passed_time":0.4629662739,"remaining_time":1.923457818},
{"learn":[4.811639392],"iteration":194,"passed_time":0.4659909676,"remaining_time":1.923706302},
{"learn":[4.804813432],"iteration":195,"passed_time":0.4681089826,"remaining_time":1.920202153},
{"learn":[4.80251613],"iteration":196,"passed_time":0.4702590509,"remaining_time":1.91684273},
{"learn":[4.800087884],"iteration":197,"passed_time":0.4723898265,"remaining_time":1.913417378},
{"learn":[4.794773135],"iteration":198,"passed_time":0.47494881,"remaining_time":1.911728627},
{"learn":[4.791664833],"iteration":199,"passed_time":0.4778289196,"remaining_time":1.911315678},
{"learn":[4.785989873],"iteration":200,"passed_time":0.4806164019,"remaining_time":1.910509976},
{"learn":[4.782387142],"iteration":201,"passed_time":0.4827835669,"remaining_time":1.907234091},
{"learn":[4.778623704],"iteration":202,"passed_time":0.4848128051,"remaining_time":1.903427614},
{"learn":[4.775772178],"iteration":203,"passed_time":0.48748881,"remaining_time":1.90216222},
{"learn":[4.77023101],"iteration":204,"passed_time":0.4904050783,"remaining_time":1.901814816},
{"learn":[4.764496689],"iteration":205,"passed_time":0.4940374227,"remaining_time":1.904202493},
{"learn":[4.763138716],"iteration":206,"passed_time":0.4959509476,"remaining_time":1.89994735},
{"learn":[4.758053283],"iteration":207,"passed_time":0.4979349611,"remaining_time":1.895983121},
{"learn":[4.755063788],"iteration":208,"passed_time":0.4998543917,"remaining_time":1.891793416},
{"learn":[4.752465267],"iteration":209,"passed_time":0.5017227464,"remaining_time":1.887433189},
{"learn":[4.748067377],"iteration":210,"passed_time":0.5041477395,"remaining_time":1.88517804},
{"learn":[4.744163298],"iteration":211,"passed_time":0.5079106009,"remaining_time":1.88789412},
{"learn":[4.736670896],"iteration":212,"passed_time":0.5099273426,"remaining_time":1.88409774},
{"learn":[4.73349255],"iteration":213,"passed_time":0.5120875362,"remaining_time":1.880844876},
{"learn":[4.731864595],"iteration":214,"passed_time":0.5140525607,"remaining_time":1.876889582},
{"learn":[4.728398311],"iteration":215,"passed_time":0.5160663111,"remaining_time":1.873129574},
{"learn":[4.723865975],"iteration":216,"passed_time":0.519410931,"remaining_time":1.874187829},
{"learn":[4.723483365],"iteration":217,"passed_time":0.5220466865,"remaining_time":1.872662885},
{"learn":[4.72095416],"iteration":218,"passed_time":0.5242914469,"remaining_time":1.869733425},
{"learn":[4.716173382],"iteration":219,"passed_time":0.5264094075,"remaining_time":1.866360627},
{"learn":[4.710563974],"iteration":220,"passed_time":0.528655382,"remaining_time":1.863450419},
{"learn":[4.707160263],"iteration":221,"passed_time":0.5305651891,"remaining_time":1.859368095},
{"learn":[4.70408351],"iteration":222,"passed_time":0.532867904,"remaining_time":1.856674267},
{"learn":[4.702501831],"iteration":223,"passed_time":0.5357886501,"remaining_time":1.856124966},
{"learn":[4.700269738],"iteration":224,"passed_time":0.5380865234,"remaining_time":1.853409136},
{"learn":[4.695346302],"iteration":225,"passed_time":0.5398952942,"remaining_time":1.849021937},
{"learn":[4.689769299],"iteration":226,"passed_time":0.5417984403,"remaining_time":1.84497883},
{"learn":[4.687919514],"iteration":227,"passed_time":0.5436610919,"remaining_time":1.840817381},
{"learn":[4.682982074],"iteration":228,"passed_time":0.5454868254,"remaining_time":1.836551714},
{"learn":[4.679578702],"iteration":229,"passed_time":0.54768774,"remaining_time":1.833563304},
{"learn":[4.675751423],"iteration":230,"passed_time":0.550345555,"remaining_time":1.832102735},
{"learn":[4.672710726],"iteration":231,"passed_time":0.5534945605,"remaining_time":1.832257856},
{"learn":[4.6690533],"iteration":232,"passed_time":0.555286224,"remaining_time":1.827916454},
{"learn":[4.667595702],"iteration":233,"passed_time":0.5569901272,"remaining_time":1.823309562},
{"learn":[4.664241291],"iteration":234,"passed_time":0.5588013294,"remaining_time":1.819076668},
{"learn":[4.662246999],"iteration":235,"passed_time":0.5604621293,"remaining_time":1.814377402},
{"learn":[4.658668443],"iteration":236,"passed_time":0.5629126198,"remaining_time":1.812246113},
{"learn":[4.658017572],"iteration":237,"passed_time":0.5653524552,"remaining_time":1.810078029},
{"learn":[4.657656705],"iteration":238,"passed_time":0.5679455257,"remaining_time":1.808395586},
{"learn":[4.653242871],"iteration":239,"passed_time":0.5699355195,"remaining_time":1.804795812},
{"learn":[4.6507302],"iteration":240,"passed_time":0.5716980675,"remaining_time":1.800493084},
{"learn":[4.647671336],"iteration":241,"passed_time":0.5735057119,"remaining_time":1.796352602},
{"learn":[4.645506007],"iteration":242,"passed_time":0.5754233005,"remaining_time":1.792573821},
{"learn":[4.641297906],"iteration":243,"passed_time":0.5783873452,"remaining_time":1.792052594},
{"learn":[4.63798107],"iteration":244,"passed_time":0.5811139087,"remaining_time":1.790779596},
{"learn":[4.635062318],"iteration":245,"passed_time":0.5834093422,"remaining_time":1.78817335},
{"learn":[4.631606017],"iteration":246,"passed_time":0.585247663,"remaining_time":1.784176074},
{"learn":[4.630215494],"iteration":247,"passed_time":0.5870533249,"remaining_time":1.780097179},
{"learn":[4.62729814],"iteration":248,"passed_time":0.5889526047,"remaining_time":1.7763189},
{"learn":[4.624691756],"iteration":249,"passed_time":0.5909847153,"remaining_time":1.772954146},
{"learn":[4.621840053],"iteration":250,"passed_time":0.5933388892,"remaining_time":1.770561068},
{"learn":[4.619602091],"iteration":251,"passed_time":0.5959756634,"remaining_time":1.769007128},
{"learn":[4.613584029],"iteration":252,"passed_time":0.5977121295,"remaining_time":1.764786406},
{"learn":[4.6119388],"iteration":253,"passed_time":0.59940872,"remaining_time":1.76046813},
{"learn":[4.60870702],"iteration":254,"passed_time":0.6010608495,"remaining_time":1.756040521},
{"learn":[4.604771557],"iteration":255,"passed_time":0.6029964465,"remaining_time":1.752458423},
{"learn":[4.604231277],"iteration":256,"passed_time":0.6049683923,"remaining_time":1.748994224},
{"learn":[4.600750354],"iteration":257,"passed_time":0.6068745222,"remaining_time":1.745352308},
{"learn":[4.596488253],"iteration":258,"passed_time":0.6091830732,"remaining_time":1.742875125},
{"learn":[4.59470784],"iteration":259,"passed_time":0.6117652442,"remaining_time":1.741178003},
{"learn":[4.588818005],"iteration":260,"passed_time":0.6135665339,"remaining_time":1.737263098},
{"learn":[4.585054174],"iteration":261,"passed_time":0.6153774171,"remaining_time":1.733391351},
{"learn":[4.581471435],"iteration":262,"passed_time":0.6172368901,"remaining_time":1.729671437},
{"learn":[4.577555199],"iteration":263,"passed_time":0.6190701517,"remaining_time":1.725892544},
{"learn":[4.57457145],"iteration":264,"passed_time":0.6208256385,"remaining_time":1.72191262},
{"learn":[4.573029224],"iteration":265,"passed_time":0.6234749214,"remaining_time":1.72041576},
{"learn":[4.571326203],"iteration":266,"passed_time":0.6258594612,"remaining_time":1.718183465},
{"learn":[4.571019224],"iteration":267,"passed_time":0.6274857596,"remaining_time":1.713879015},
{"learn":[4.565766631],"iteration":268,"passed_time":0.6291607777,"remaining_time":1.709726872},
{"learn":[4.563383471],"iteration":269,"passed_time":0.6311168138,"remaining_time":1.706352867},
{"learn":[4.558165805],"iteration":270,"passed_time":0.6329020751,"remaining_time":1.702529936},
{"learn":[4.55629209],"iteration":271,"passed_time":0.6347056124,"remaining_time":1.698770904},
{"learn":[4.549383848],"iteration":272,"passed_time":0.63666627,"remaining_time":1.695444609},
{"learn":[4.546227503],"iteration":273,"passed_time":0.6392587564,"remaining_time":1.693802398},
{"learn":[4.540620977],"iteration":274,"passed_time":0.641451562,"remaining_time":1.691099572},
{"learn":[4.532898237],"iteration":275,"passed_time":0.6433383463,"remaining_time":1.687597691},
{"learn":[4.529757367],"iteration":276,"passed_time":0.6452360968,"remaining_time":1.684136094},
{"learn":[4.52579294],"iteration":277,"passed_time":0.6471231452,"remaining_time":1.680657953},
{"learn":[4.521572155],"iteration":278,"passed_time":0.6491205757,"remaining_time":1.67747647},
{"learn":[4.518818099],"iteration":279,"passed_time":0.6510629588,"remaining_time":1.674161894},
{"learn":[4.514012334],"iteration":280,"passed_time":0.6536918405,"remaining_time":1.672613642},
{"learn":[4.508331416],"iteration":281,"passed_time":0.6558691072,"remaining_time":1.669907869},
{"learn":[4.506038537],"iteration":282,"passed_time":0.6579027746,"remaining_time":1.666842012},
{"learn":[4.505805643],"iteration":283,"passed_time":0.6598977969,"remaining_time":1.663685995},
{"learn":[4.501550352],"iteration":284,"passed_time":0.66176944,"remaining_time":1.660228595},
{"learn":[4.494692643],"iteration":285,"passed_time":0.6637128012,"remaining_time":1.656961329},
{"learn":[4.489330245],"iteration":286,"passed_time":0.6655916175,"remaining_time":1.653542938},
{"learn":[4.484826955],"iteration":287,"passed_time":0.6680791323,"remaining_time":1.651640077},
{"learn":[4.478285428],"iteration":288,"passed_time":0.6702788444,"remaining_time":1.649025115},
{"learn":[4.475311671],"iteration":289,"passed_time":0.6720902753,"remaining_time":1.645462398},
{"learn":[4.471581298],"iteration":290,"passed_time":0.673937435,"remaining_time":1.641998768},
{"learn":[4.469164956],"iteration":291,"passed_time":0.6756910042,"remaining_time":1.638319284},
{"learn":[4.462068024],"iteration":292,"passed_time":0.6775850056,"remaining_time":1.634991805},
{"learn":[4.458540976],"iteration":293,"passed_time":0.6793924905,"remaining_time":1.631466321},
{"learn":[4.455757458],"iteration":294,"passed_time":0.6811317787,"remaining_time":1.627789505},
{"learn":[4.453027414],"iteration":295,"passed_time":0.6832949038,"remaining_time":1.625133825},
{"learn":[4.450659338],"iteration":296,"passed_time":0.6857783622,"remaining_time":1.623239692},
{"learn":[4.444696901],"iteration":297,"passed_time":0.6890510222,"remaining_time":1.62320073},
{"learn":[4.442052813],"iteration":298,"passed_time":0.6910370821,"remaining_time":1.620123728},
{"learn":[4.440036756],"iteration":299,"passed_time":0.69280145,"remaining_time":1.616536717},
{"learn":[4.435017051],"iteration":300,"passed_time":0.6946492482,"remaining_time":1.613155563},
{"learn":[4.429962125],"iteration":301,"passed_time":0.6965319788,"remaining_time":1.609865302},
{"learn":[4.427666256],"iteration":302,"passed_time":0.6994855993,"remaining_time":1.609047732},
{"learn":[4.425030004],"iteration":303,"passed_time":0.7015815433,"remaining_time":1.606252481},
{"learn":[4.422588771],"iteration":304,"passed_time":0.7036739669,"remaining_time":1.603453793},
{"learn":[4.418936667],"iteration":305,"passed_time":0.7058072996,"remaining_time":1.600752503},
{"learn":[4.416887976],"iteration":306,"passed_time":0.7078822963,"remaining_time":1.597923229},
{"learn":[4.413773354],"iteration":307,"passed_time":0.7099014118,"remaining_time":1.594973302},
{"learn":[4.411129391],"iteration":308,"passed_time":0.7118261848,"remaining_time":1.591818426},
{"learn":[4.40850819],"iteration":309,"passed_time":0.7145576807,"remaining_time":1.590467096},
{"learn":[4.404880292],"iteration":310,"passed_time":0.71752011,"remaining_time":1.589618507},
{"learn":[4.404593827],"iteration":311,"passed_time":0.7199119234,"remaining_time":1.587498088},
{"learn":[4.402139942],"iteration":312,"passed_time":0.7235915008,"remaining_time":1.588202432},
{"learn":[4.400284725],"iteration":313,"passed_time":0.7259892718,"remaining_time":1.586078473},
{"learn":[4.395805521],"iteration":314,"passed_time":0.7306861735,"remaining_time":1.588952473},
{"learn":[4.392838833],"iteration":315,"passed_time":0.7329105327,"remaining_time":1.586426596},
{"learn":[4.389213061],"iteration":316,"passed_time":0.735180012,"remaining_time":1.583999837},
{"learn":[4.3861981],"iteration":317,"passed_time":0.7371798079,"remaining_time":1.580995689},
{"learn":[4.385054234],"iteration":318,"passed_time":0.7389186536,"remaining_time":1.577440762},
{"learn":[4.379364607],"iteration":319,"passed_time":0.7407895532,"remaining_time":1.5741778},
{"learn":[4.378387619],"iteration":320,"passed_time":0.7435030439,"remaining_time":1.572705816},
{"learn":[4.375816727],"iteration":321,"passed_time":0.7462762738,"remaining_time":1.571351906},
{"learn":[4.374600202],"iteration":322,"passed_time":0.7494793244,"remaining_time":1.570890101},
{"learn":[4.37098897],"iteration":323,"passed_time":0.7521635181,"remaining_time":1.569328822},
{"learn":[4.367418484],"iteration":324,"passed_time":0.7541451229,"remaining_time":1.566301409},
{"learn":[4.363584638],"iteration":325,"passed_time":0.7561345696,"remaining_time":1.563296625},
{"learn":[4.360770706],"iteration":326,"passed_time":0.7583593217,"remaining_time":1.560782335},
{"learn":[4.358675808],"iteration":327,"passed_time":0.7612035709,"remaining_time":1.559539023},
{"learn":[4.354228195],"iteration":328,"passed_time":0.7638523627,"remaining_time":1.557887341},
{"learn":[4.353773425],"iteration":329,"passed_time":0.7660749548,"remaining_time":1.555364302},
{"learn":[4.351648009],"iteration":330,"passed_time":0.7682367554,"remaining_time":1.55272021},
{"learn":[4.348209927],"iteration":331,"passed_time":0.7705805669,"remaining_time":1.550445237},
{"learn":[4.345852733],"iteration":332,"passed_time":0.7730844053,"remaining_time":1.548490385},
{"learn":[4.34237339],"iteration":333,"passed_time":0.7766425237,"remaining_time":1.548634493},
{"learn":[4.340814362],"iteration":334,"passed_time":0.779214149,"remaining_time":1.546798236},
{"learn":[4.339707068],"iteration":335,"passed_time":0.7812953309,"remaining_time":1.543988392},
{"learn":[4.335430786],"iteration":336,"passed_time":0.7833757518,"remaining_time":1.541181375},
{"learn":[4.33521887],"iteration":337,"passed_time":0.7862132592,"remaining_time":1.539861472},
{"learn":[4.328507238],"iteration":338,"passed_time":0.7904363391,"remaining_time":1.541234278},
{"learn":[4.326140732],"iteration":339,"passed_time":0.7942210096,"remaining_time":1.541723136},
{"learn":[4.323785636],"iteration":340,"passed_time":0.7967091354,"remaining_time":1.539681291},
{"learn":[4.320632534],"iteration":341,"passed_time":0.7985548159,"remaining_time":1.536400786},
{"learn":[4.31973724],"iteration":342,"passed_time":0.8006617128,"remaining_time":1.533628995},
{"learn":[4.318000924],"iteration":343,"passed_time":0.8032962003,"remaining_time":1.531867173},
{"learn":[4.312713628],"iteration":344,"passed_time":0.8056432961,"remaining_time":1.529554664},
{"learn":[4.308220789],"iteration":345,"passed_time":0.8081004375,"remaining_time":1.52744996},
{"learn":[4.305890947],"iteration":346,"passed_time":0.8101401569,"remaining_time":1.524557702},
{"learn":[4.305137856],"iteration":347,"passed_time":0.8122250567,"remaining_time":1.521754991},
{"learn":[4.304787172],"iteration":348,"passed_time":0.8148460163,"remaining_time":1.519956323},
{"learn":[4.30350134],"iteration":349,"passed_time":0.817143793,"remaining_time":1.517552758},
{"learn":[4.30293809],"iteration":350,"passed_time":0.8196020889,"remaining_time":1.515446597},
{"learn":[4.299548459],"iteration":351,"passed_time":0.8221705851,"remaining_time":1.513541304},
{"learn":[4.294768408],"iteration":352,"passed_time":0.8243515073,"remaining_time":1.510921885},
{"learn":[4.294581479],"iteration":353,"passed_time":0.8264997029,"remaining_time":1.508245221},
{"learn":[4.292551604],"iteration":354,"passed_time":0.8286072536,"remaining_time":1.505497686},
{"learn":[4.288628894],"iteration":355,"passed_time":0.8307761281,"remaining_time":1.502864681},
{"learn":[4.287802767],"iteration":356,"passed_time":0.8332056096,"remaining_time":1.500703661},
{"learn":[4.284566905],"iteration":357,"passed_time":0.8362735766,"remaining_time":1.499686135},
{"learn":[4.27890232],"iteration":358,"passed_time":0.8392677782,"remaining_time":1.498525476},
{"learn":[4.276938023],"iteration":359,"passed_time":0.8415314927,"remaining_time":1.496055987},
{"learn":[4.273425094],"iteration":360,"passed_time":0.8433577501,"remaining_time":1.492813303},
{"learn":[4.269726505],"iteration":361,"passed_time":0.8452329584,"remaining_time":1.489664717},
{"learn":[4.265565857],"iteration":362,"passed_time":0.8479129051,"remaining_time":1.487935318},
{"learn":[4.262117173],"iteration":363,"passed_time":0.8516147928,"remaining_time":1.487986286},
{"learn":[4.259185148],"iteration":364,"passed_time":0.8545092963,"remaining_time":1.486612063},
{"learn":[4.257668507],"iteration":365,"passed_time":0.8563502587,"remaining_time":1.483404547},
{"learn":[4.253432436],"iteration":366,"passed_time":0.8581252832,"remaining_time":1.480090747},
{"learn":[4.250216667],"iteration":367,"passed_time":0.8599260195,"remaining_time":1.476829468},
{"learn":[4.24514828],"iteration":368,"passed_time":0.8622740674,"remaining_time":1.474512023},
{"learn":[4.244015772],"iteration":369,"passed_time":0.8655665777,"remaining_time":1.473802551},
{"learn":[4.240329192],"iteration":370,"passed_time":0.8684944426,"remaining_time":1.472460928},
{"learn":[4.236718014],"iteration":371,"passed_time":0.8705391705,"remaining_time":1.46961989},
{"learn":[4.233495944],"iteration":372,"passed_time":0.8723013679,"remaining_time":1.466308198},
{"learn":[4.230357491],"iteration":373,"passed_time":0.8740892485,"remaining_time":1.46304778},
{"learn":[4.227381215],"iteration":374,"passed_time":0.8759598703,"remaining_time":1.459933117},
{"learn":[4.226169067],"iteration":375,"passed_time":0.8783748405,"remaining_time":1.457728459},
{"learn":[4.225963861],"iteration":376,"passed_time":0.8811587212,"remaining_time":1.456132316},
{"learn":[4.224346548],"iteration":377,"passed_time":0.8846196516,"remaining_time":1.455643977},
{"learn":[4.222595381],"iteration":378,"passed_time":0.886524317,"remaining_time":1.452589976},
{"learn":[4.219700938],"iteration":379,"passed_time":0.8884877984,"remaining_time":1.449637987},
{"learn":[4.216356207],"iteration":380,"passed_time":0.8905132194,"remaining_time":1.446791818},
{"learn":[4.214326494],"iteration":381,"passed_time":0.8930741622,"remaining_time":1.444816315},
{"learn":[4.212901398],"iteration":382,"passed_time":0.8961774351,"remaining_time":1.443711429},
{"learn":[4.211331091],"iteration":383,"passed_time":0.8991368943,"remaining_time":1.442365435},
{"learn":[4.208624791],"iteration":384,"passed_time":0.9010278433,"remaining_time":1.439304217},
{"learn":[4.204659106],"iteration":385,"passed_time":0.9031525436,"remaining_time":1.436620885},
{"learn":[4.202968852],"iteration":386,"passed_time":0.9049334326,"remaining_time":1.433395851},
{"learn":[4.197261935],"iteration":387,"passed_time":0.9068658203,"remaining_time":1.430417222},
{"learn":[4.196934403],"iteration":388,"passed_time":0.9099951789,"remaining_time":1.429324047},
{"learn":[4.192479929],"iteration":389,"passed_time":0.9127345631,"remaining_time":1.42761047},
{"learn":[4.190243116],"iteration":390,"passed_time":0.9147140048,"remaining_time":1.424708002},
{"learn":[4.185852431],"iteration":391,"passed_time":0.9165927177,"remaining_time":1.421654011},
{"learn":[4.180967944],"iteration":392,"passed_time":0.9183971464,"remaining_time":1.418491267},
{"learn":[4.178283162],"iteration":393,"passed_time":0.9203215603,"remaining_time":1.415519963},
{"learn":[4.176341157],"iteration":394,"passed_time":0.922495071,"remaining_time":1.412935489},
{"learn":[4.176041504],"iteration":395,"passed_time":0.924780179,"remaining_time":1.410523303},
{"learn":[4.175564513],"iteration":396,"passed_time":0.9277787601,"remaining_time":1.409195447},
{"learn":[4.170830274],"iteration":397,"passed_time":0.9299484575,"remaining_time":1.406605456},
{"learn":[4.167804808],"iteration":398,"passed_time":0.9319327181,"remaining_time":1.403738255},
{"learn":[4.165860548],"iteration":399,"passed_time":0.9337265637,"remaining_time":1.400589846},
{"learn":[4.160950571],"iteration":400,"passed_time":0.9357951139,"remaining_time":1.397858537},
{"learn":[4.158544115],"iteration":401,"passed_time":0.9381318139,"remaining_time":1.395529415},
{"learn":[4.154448767],"iteration":402,"passed_time":0.941185999,"remaining_time":1.39426313},
{"learn":[4.15197457],"iteration":403,"passed_time":0.9439705551,"remaining_time":1.392590225},
{"learn":[4.149562679],"iteration":404,"passed_time":0.9458839205,"remaining_time":1.389631933},
{"learn":[4.149327961],"iteration":405,"passed_time":0.9477923249,"remaining_time":1.38667153},
{"learn":[4.147444889],"iteration":406,"passed_time":0.9495155905,"remaining_time":1.383446548},
{"learn":[4.147254809],"iteration":407,"passed_time":0.9513941079,"remaining_time":1.380454196},
{"learn":[4.144589165],"iteration":408,"passed_time":0.9546150275,"remaining_time":1.379407045},
{"learn":[4.141691034],"iteration":409,"passed_time":0.957599279,"remaining_time":1.378008719},
{"learn":[4.138893468],"iteration":410,"passed_time":0.9603368973,"remaining_time":1.376249227},
{"learn":[4.136964597],"iteration":411,"passed_time":0.9622772451,"remaining_time":1.373347136},
{"learn":[4.133773523],"iteration":412,"passed_time":0.9644644596,"remaining_time":1.370800576},
{"learn":[4.131363444],"iteration":413,"passed_time":0.9665828987,"remaining_time":1.368158402},
{"learn":[4.130228592],"iteration":414,"passed_time":0.9698676464,"remaining_time":1.367162827},
{"learn":[4.12884186],"iteration":415,"passed_time":0.9727071701,"remaining_time":1.36553122},
{"learn":[4.12413494],"iteration":416,"passed_time":0.9747040751,"remaining_time":1.362715769},
{"learn":[4.119422508],"iteration":417,"passed_time":0.9770512052,"remaining_time":1.360391869},
{"learn":[4.117038244],"iteration":418,"passed_time":0.9795316006,"remaining_time":1.358252649},
{"learn":[4.116067631],"iteration":419,"passed_time":0.9824133467,"remaining_time":1.35666605},
{"learn":[4.110343455],"iteration":420,"passed_time":0.9863995902,"remaining_time":1.35659231},
{"learn":[4.105604544],"iteration":421,"passed_time":0.9889800622,"remaining_time":1.354574588},
{"learn":[4.103390131],"iteration":422,"passed_time":0.9911742662,"remaining_time":1.352027309},
{"learn":[4.096724402],"iteration":423,"passed_time":0.9931061496,"remaining_time":1.349125335},
{"learn":[4.093431279],"iteration":424,"passed_time":0.9949021593,"remaining_time":1.346044098},
{"learn":[4.091412744],"iteration":425,"passed_time":0.997543762,"remaining_time":1.344108261},
{"learn":[4.091192901],"iteration":426,"passed_time":1.000367255,"remaining_time":1.342413201},
{"learn":[4.088994581],"iteration":427,"passed_time":1.003251155,"remaining_time":1.3407936},
{"learn":[4.087845355],"iteration":428,"passed_time":1.005374129,"remaining_time":1.33815531},
{"learn":[4.083650279],"iteration":429,"passed_time":1.007172869,"remaining_time":1.335089617},
{"learn":[4.079840652],"iteration":430,"passed_time":1.008993616,"remaining_time":1.332058858},
{"learn":[4.075707828],"iteration":431,"passed_time":1.011071142,"remaining_time":1.329371317},
{"learn":[4.071345409],"iteration":432,"passed_time":1.013747571,"remaining_time":1.327470837},
{"learn":[4.067460475],"iteration":433,"passed_time":1.017032423,"remaining_time":1.326360257},
{"learn":[4.064914749],"iteration":434,"passed_time":1.019163712,"remaining_time":1.323741374},
{"learn":[4.063823175],"iteration":435,"passed_time":1.02096671,"remaining_time":1.320700055},
{"learn":[4.058898471],"iteration":436,"passed_time":1.023136806,"remaining_time":1.31813735},
{"learn":[4.054120355],"iteration":437,"passed_time":1.025133686,"remaining_time":1.315354181},
{"learn":[4.052715901],"iteration":438,"passed_time":1.027827128,"remaining_time":1.313464736},
{"learn":[4.052114167],"iteration":439,"passed_time":1.032438132,"remaining_time":1.314012168},
{"learn":[4.051377267],"iteration":440,"passed_time":1.03438237,"remaining_time":1.311155884},
{"learn":[4.049275336],"iteration":441,"passed_time":1.036391803,"remaining_time":1.308386032},
{"learn":[4.047099198],"iteration":442,"passed_time":1.038528457,"remaining_time":1.305779573},
{"learn":[4.044348685],"iteration":443,"passed_time":1.040539905,"remaining_time":1.30301844},
{"learn":[4.042822379],"iteration":444,"passed_time":1.043071106,"remaining_time":1.300908908},
{"learn":[4.041258611],"iteration":445,"passed_time":1.047068166,"remaining_time":1.300618305},
{"learn":[4.040044254],"iteration":446,"passed_time":1.049272349,"remaining_time":1.298093085},
{"learn":[4.036860137],"iteration":447,"passed_time":1.051852919,"remaining_time":1.29603306},
{"learn":[4.036372284],"iteration":448,"passed_time":1.054250883,"remaining_time":1.293746629},
{"learn":[4.03368231],"iteration":449,"passed_time":1.056690661,"remaining_time":1.291510808},
{"learn":[4.032439519],"iteration":450,"passed_time":1.06003177,"remaining_time":1.290371267},
{"learn":[4.032008634],"iteration":451,"passed_time":1.063341317,"remaining_time":1.28918372},
{"learn":[4.030034932],"iteration":452,"passed_time":1.066064429,"remaining_time":1.287278681},
{"learn":[4.028173412],"iteration":453,"passed_time":1.068657746,"remaining_time":1.285213941},
{"learn":[4.023806097],"iteration":454,"passed_time":1.070916819,"remaining_time":1.28274652},
{"learn":[4.020239186],"iteration":455,"passed_time":1.07468883,"remaining_time":1.282084921},
{"learn":[4.017384838],"iteration":456,"passed_time":1.078259797,"remaining_time":1.28117083},
{"learn":[4.016468229],"iteration":457,"passed_time":1.081055532,"remaining_time":1.279327725},
{"learn":[4.014530169],"iteration":458,"passed_time":1.08356264,"remaining_time":1.27714028},
{"learn":[4.012884822],"iteration":459,"passed_time":1.085761237,"remaining_time":1.274589278},
{"learn":[4.008924707],"iteration":460,"passed_time":1.089590506,"remaining_time":1.273946383},
{"learn":[4.008286778],"iteration":461,"passed_time":1.092710836,"remaining_time":1.272464134},
{"learn":[4.006444202],"iteration":462,"passed_time":1.096588064,"remaining_time":1.271852679},
{"learn":[4.003284363],"iteration":463,"passed_time":1.1003791,"remaining_time":1.271127581},
{"learn":[3.999811484],"iteration":464,"passed_time":1.105041375,"remaining_time":1.27139169},
{"learn":[3.997483319],"iteration":465,"passed_time":1.109743735,"remaining_time":1.271680589},
{"learn":[3.99708333],"iteration":466,"passed_time":1.112354297,"remaining_time":1.269560686},
{"learn":[3.995860263],"iteration":467,"passed_time":1.114371354,"remaining_time":1.266764018},
{"learn":[3.994131111],"iteration":468,"passed_time":1.116451315,"remaining_time":1.264041894},
{"learn":[3.993125499],"iteration":469,"passed_time":1.120412711,"remaining_time":1.26344412},
{"learn":[3.992954084],"iteration":470,"passed_time":1.123148016,"remaining_time":1.26145499},
{"learn":[3.990635743],"iteration":471,"passed_time":1.125513964,"remaining_time":1.259049519},
{"learn":[3.986678254],"iteration":472,"passed_time":1.127614411,"remaining_time":1.256348403},
{"learn":[3.986393291],"iteration":473,"passed_time":1.129507276,"remaining_time":1.253419467},
{"learn":[3.986152671],"iteration":474,"passed_time":1.131574399,"remaining_time":1.250687493},
{"learn":[3.985596662],"iteration":475,"passed_time":1.134405388,"remaining_time":1.248799208},
{"learn":[3.983853457],"iteration":476,"passed_time":1.137311509,"remaining_time":1.246989349},
{"learn":[3.983263928],"iteration":477,"passed_time":1.139495148,"remaining_time":1.244385914},
{"learn":[3.980067202],"iteration":478,"passed_time":1.141616561,"remaining_time":1.241716552},
{"learn":[3.978115407],"iteration":479,"passed_time":1.14363477,"remaining_time":1.238937667},
{"learn":[3.972661644],"iteration":480,"passed_time":1.145661249,"remaining_time":1.23617087},
{"learn":[3.969938254],"iteration":481,"passed_time":1.149638484,"remaining_time":1.235503599},
{"learn":[3.968211434],"iteration":482,"passed_time":1.153378916,"remaining_time":1.234569151},
{"learn":[3.966113368],"iteration":483,"passed_time":1.155819117,"remaining_time":1.23223691},
{"learn":[3.962246044],"iteration":484,"passed_time":1.157910075,"remaining_time":1.229533379},
{"learn":[3.961319703],"iteration":485,"passed_time":1.15981645,"remaining_time":1.226637151},
{"learn":[3.96078191],"iteration":486,"passed_time":1.162034681,"remaining_time":1.224073494},
{"learn":[3.958913633],"iteration":487,"passed_time":1.164999876,"remaining_time":1.222294952},
{"learn":[3.957428286],"iteration":488,"passed_time":1.16763087,"remaining_time":1.22016232},
{"learn":[3.952641965],"iteration":489,"passed_time":1.169637782,"remaining_time":1.217378099},
{"learn":[3.951486786],"iteration":490,"passed_time":1.171444,"remaining_time":1.214388994},
{"learn":[3.94938344],"iteration":491,"passed_time":1.173041834,"remaining_time":1.211189536},
{"learn":[3.947297924],"iteration":492,"passed_time":1.174841146,"remaining_time":1.208203775},
{"learn":[3.946284886],"iteration":493,"passed_time":1.176973043,"remaining_time":1.205563481},
{"learn":[3.943288204],"iteration":494,"passed_time":1.179552716,"remaining_time":1.203382064},
{"learn":[3.943076488],"iteration":495,"passed_time":1.182141839,"remaining_time":1.201208643},
{"learn":[3.942347078],"iteration":496,"passed_time":1.184095913,"remaining_time":1.198390833},
{"learn":[3.940251541],"iteration":497,"passed_time":1.18592812,"remaining_time":1.195453647},
{"learn":[3.939011019],"iteration":498,"passed_time":1.187824114,"remaining_time":1.192584932},
{"learn":[3.938760512],"iteration":499,"passed_time":1.189558415,"remaining_time":1.189558415},
{"learn":[3.934522727],"iteration":500,"passed_time":1.192374752,"remaining_time":1.187614773},
{"learn":[3.930091193],"iteration":501,"passed_time":1.195549449,"remaining_time":1.186023158},
{"learn":[3.927671752],"iteration":502,"passed_time":1.199699351,"remaining_time":1.185388822},
{"learn":[3.927280041],"iteration":503,"passed_time":1.202197695,"remaining_time":1.183115192},
{"learn":[3.925987561],"iteration":504,"passed_time":1.204312983,"remaining_time":1.180465201},
{"learn":[3.921645957],"iteration":505,"passed_time":1.206253642,"remaining_time":1.177646836},
{"learn":[3.920333743],"iteration":506,"passed_time":1.20877375,"remaining_time":1.175395382},
{"learn":[3.918659461],"iteration":507,"passed_time":1.211912996,"remaining_time":1.173742508},
{"learn":[3.916124385],"iteration":508,"passed_time":1.21421308,"remaining_time":1.171274307},
{"learn":[3.913849268],"iteration":509,"passed_time":1.21606459,"remaining_time":1.168375782},
{"learn":[3.912826119],"iteration":510,"passed_time":1.217794702,"remaining_time":1.165365185},
{"learn":[3.910034145],"iteration":511,"passed_time":1.219880377,"remaining_time":1.162698484},
{"learn":[3.90792379],"iteration":512,"passed_time":1.222364243,"remaining_time":1.160412059},
{"learn":[3.907823851],"iteration":513,"passed_time":1.225529498,"remaining_time":1.158769137},
{"learn":[3.904527401],"iteration":514,"passed_time":1.227702423,"remaining_time":1.156185777},
{"learn":[3.903378283],"iteration":515,"passed_time":1.229816961,"remaining_time":1.153549243},
{"learn":[3.902170135],"iteration":516,"passed_time":1.231737703,"remaining_time":1.150733676},
{"learn":[3.899435429],"iteration":517,"passed_time":1.233872061,"remaining_time":1.148120334},
{"learn":[3.897497505],"iteration":518,"passed_time":1.235792699,"remaining_time":1.145310767},
{"learn":[3.896426119],"iteration":519,"passed_time":1.23803843,"remaining_time":1.142804704},
{"learn":[3.896044669],"iteration":520,"passed_time":1.240757256,"remaining_time":1.140734598},
{"learn":[3.892795942],"iteration":521,"passed_time":1.24303825,"remaining_time":1.138261079},
{"learn":[3.892413888],"iteration":522,"passed_time":1.244832738,"remaining_time":1.135344581},
{"learn":[3.891738985],"iteration":523,"passed_time":1.246587187,"remaining_time":1.132395994},
{"learn":[3.88822057],"iteration":524,"passed_time":1.24845697,"remaining_time":1.129556306},
{"learn":[3.883837053],"iteration":525,"passed_time":1.250388606,"remaining_time":1.126776044},
{"learn":[3.881769742],"iteration":526,"passed_time":1.253010369,"remaining_time":1.124618415},
{"learn":[3.880356898],"iteration":527,"passed_time":1.256683773,"remaining_time":1.12339913},
{"learn":[3.879250273],"iteration":528,"passed_time":1.258618414,"remaining_time":1.120622445},
{"learn":[3.877174493],"iteration":529,"passed_time":1.260520765,"remaining_time":1.117820301},
{"learn":[3.875854201],"iteration":530,"passed_time":1.262736685,"remaining_time":1.115298503},
{"learn":[3.873189396],"iteration":531,"passed_time":1.264610652,"remaining_time":1.11247704},
{"learn":[3.871583368],"iteration":532,"passed_time":1.266488116,"remaining_time":1.109662195},
{"learn":[3.869622679],"iteration":533,"passed_time":1.268878588,"remaining_time":1.107298543},
{"learn":[3.866860164],"iteration":534,"passed_time":1.272136602,"remaining_time":1.105688822},
{"learn":[3.864498444],"iteration":535,"passed_time":1.273921574,"remaining_time":1.10279778},
{"learn":[3.861416322],"iteration":536,"passed_time":1.275524157,"remaining_time":1.099753603},
{"learn":[3.860265769],"iteration":537,"passed_time":1.277461545,"remaining_time":1.097002293},
{"learn":[3.859328725],"iteration":538,"passed_time":1.279255982,"remaining_time":1.094131739},
{"learn":[3.858521278],"iteration":539,"passed_time":1.281059893,"remaining_time":1.091273242},
{"learn":[3.85599111],"iteration":540,"passed_time":1.28347629,"remaining_time":1.088938294},
{"learn":[3.852379816],"iteration":541,"passed_time":1.286927003,"remaining_time":1.087477061},
{"learn":[3.851327537],"iteration":542,"passed_time":1.289219631,"remaining_time":1.085033833},
{"learn":[3.847854898],"iteration":543,"passed_time":1.291390461,"remaining_time":1.082489063},
{"learn":[3.847083414],"iteration":544,"passed_time":1.293353132,"remaining_time":1.079771881},
{"learn":[3.845397429],"iteration":545,"passed_time":1.29511682,"remaining_time":1.076892008},
{"learn":[3.841933528],"iteration":546,"passed_time":1.29682156,"remaining_time":1.073967398},
{"learn":[3.840996474],"iteration":547,"passed_time":1.298952981,"remaining_time":1.071399174},
{"learn":[3.838355966],"iteration":548,"passed_time":1.301462428,"remaining_time":1.069143087},
{"learn":[3.83342799],"iteration":549,"passed_time":1.303485943,"remaining_time":1.066488499},
{"learn":[3.828161535],"iteration":550,"passed_time":1.305278961,"remaining_time":1.063648373},
{"learn":[3.823502399],"iteration":551,"passed_time":1.307059082,"remaining_time":1.060801574},
{"learn":[3.820068862],"iteration":552,"passed_time":1.309039371,"remaining_time":1.058120432},
{"learn":[3.817951642],"iteration":553,"passed_time":1.310788836,"remaining_time":1.055255995},
{"learn":[3.815785958],"iteration":554,"passed_time":1.312765966,"remaining_time":1.052578117},
{"learn":[3.81503012],"iteration":555,"passed_time":1.315607083,"remaining_time":1.050592706},
{"learn":[3.813529315],"iteration":556,"passed_time":1.317488225,"remaining_time":1.047840725},
{"learn":[3.808881326],"iteration":557,"passed_time":1.319262506,"remaining_time":1.045007218},
{"learn":[3.808740434],"iteration":558,"passed_time":1.320862018,"remaining_time":1.042039624},
{"learn":[3.80714352],"iteration":559,"passed_time":1.322585809,"remaining_time":1.039174564},
{"learn":[3.80573346],"iteration":560,"passed_time":1.324553431,"remaining_time":1.036504378},
{"learn":[3.803370052],"iteration":561,"passed_time":1.326169627,"remaining_time":1.033562805},
{"learn":[3.803215211],"iteration":562,"passed_time":1.327916688,"remaining_time":1.030727518},
{"learn":[3.801309667],"iteration":563,"passed_time":1.331020721,"remaining_time":1.028945096},
{"learn":[3.800003847],"iteration":564,"passed_time":1.332852369,"remaining_time":1.026178373},
{"learn":[3.798026138],"iteration":565,"passed_time":1.334642717,"remaining_time":1.023383285},
{"learn":[3.794745847],"iteration":566,"passed_time":1.33635084,"remaining_time":1.020528948},
{"learn":[3.794312041],"iteration":567,"passed_time":1.337994394,"remaining_time":1.017629539},
{"learn":[3.792205926],"iteration":568,"passed_time":1.33988669,"remaining_time":1.014922959},
{"learn":[3.788991061],"iteration":569,"passed_time":1.341649994,"remaining_time":1.012121926},
{"learn":[3.787391572],"iteration":570,"passed_time":1.343547747,"remaining_time":1.00942554},
{"learn":[3.7826445],"iteration":571,"passed_time":1.346548352,"remaining_time":1.007557159},
{"learn":[3.781700331],"iteration":572,"passed_time":1.348364681,"remaining_time":1.004802301},
{"learn":[3.780045374],"iteration":573,"passed_time":1.350187911,"remaining_time":1.002055837},
{"learn":[3.775462644],"iteration":574,"passed_time":1.351975034,"remaining_time":0.9992858945},
{"learn":[3.773711943],"iteration":575,"passed_time":1.353679637,"remaining_time":0.9964586214},
{"learn":[3.772415806],"iteration":576,"passed_time":1.355357675,"remaining_time":0.9936157655},
{"learn":[3.770170875],"iteration":577,"passed_time":1.357080601,"remaining_time":0.9908097125},
{"learn":[3.765166479],"iteration":578,"passed_time":1.35885828,"remaining_time":0.9880472124},
{"learn":[3.763976102],"iteration":579,"passed_time":1.361381899,"remaining_time":0.9858282715},
{"learn":[3.760761708],"iteration":580,"passed_time":1.362985167,"remaining_time":0.9829445521},
{"learn":[3.758155662],"iteration":581,"passed_time":1.364705065,"remaining_time":0.9801489985},
{"learn":[3.756844548],"iteration":582,"passed_time":1.366366083,"remaining_time":0.9773150203},
{"learn":[3.753098923],"iteration":583,"passed_time":1.368110156,"remaining_time":0.9745442206},
{"learn":[3.751618946],"iteration":584,"passed_time":1.369960017,"remaining_time":0.9718519781},
{"learn":[3.751398464],"iteration":585,"passed_time":1.371591568,"remaining_time":0.9690083775},
{"learn":[3.749920103],"iteration":586,"passed_time":1.373467169,"remaining_time":0.9663406146},
{"learn":[3.748237465],"iteration":587,"passed_time":1.376733567,"remaining_time":0.9646500505},
{"learn":[3.746021536],"iteration":588,"passed_time":1.378941194,"remaining_time":0.9622153326},
{"learn":[3.74417648],"iteration":589,"passed_time":1.381215426,"remaining_time":0.9598276687},
{"learn":[3.738788389],"iteration":590,"passed_time":1.383616192,"remaining_time":0.9575279566},
{"learn":[3.736021611],"iteration":591,"passed_time":1.38546124,"remaining_time":0.9548449089},
{"learn":[3.734546151],"iteration":592,"passed_time":1.387363656,"remaining_time":0.9522040608},
{"learn":[3.733527479],"iteration":593,"passed_time":1.389750033,"remaining_time":0.9498964874},
{"learn":[3.733026392],"iteration":594,"passed_time":1.392070723,"remaining_time":0.9475439377},
{"learn":[3.730314752],"iteration":595,"passed_time":1.393889797,"remaining_time":0.944851473},
{"learn":[3.727342596],"iteration":596,"passed_time":1.395644241,"remaining_time":0.9421183068},
{"learn":[3.725459604],"iteration":597,"passed_time":1.397466047,"remaining_time":0.9394336969},
{"learn":[3.723158842],"iteration":598,"passed_time":1.399394377,"remaining_time":0.9368232807},
{"learn":[3.722362756],"iteration":599,"passed_time":1.40139767,"remaining_time":0.9342651136},
{"learn":[3.721443615],"iteration":600,"passed_time":1.403663538,"remaining_time":0.9318831142},
{"learn":[3.720743486],"iteration":601,"passed_time":1.406307517,"remaining_time":0.9297514811},
{"learn":[3.720215334],"iteration":602,"passed_time":1.408054424,"remaining_time":0.9270275394},
{"learn":[3.719436563],"iteration":603,"passed_time":1.409739347,"remaining_time":0.9242661947},
{"learn":[3.715046574],"iteration":604,"passed_time":1.411532295,"remaining_time":0.9215789366},
{"learn":[3.71443396],"iteration":605,"passed_time":1.413353275,"remaining_time":0.9189128556},
{"learn":[3.712938941],"iteration":606,"passed_time":1.415507583,"remaining_time":0.9164653706},
{"learn":[3.712814764],"iteration":607,"passed_time":1.417840848,"remaining_time":0.9141342309},
{"learn":[3.71235348],"iteration":608,"passed_time":1.420176285,"remaining_time":0.9118044784},
{"learn":[3.711223749],"iteration":609,"passed_time":1.42197044,"remaining_time":0.9091286418},
{"learn":[3.710755648],"iteration":610,"passed_time":1.423754252,"remaining_time":0.9064491067},
{"learn":[3.708668039],"iteration":611,"passed_time":1.425575271,"remaining_time":0.9037960868},
{"learn":[3.705623591],"iteration":612,"passed_time":1.427419209,"remaining_time":0.9011602508},
{"learn":[3.704045802],"iteration":613,"passed_time":1.429408813,"remaining_time":0.8986185699},
{"learn":[3.699915209],"iteration":614,"passed_time":1.431181938,"remaining_time":0.8959431642},
{"learn":[3.696182221],"iteration":615,"passed_time":1.434806896,"remaining_time":0.894425078},
{"learn":[3.694263278],"iteration":616,"passed_time":1.436598755,"remaining_time":0.8917622743},
{"learn":[3.693810229],"iteration":617,"passed_time":1.438503009,"remaining_time":0.889171763},
{"learn":[3.690900932],"iteration":618,"passed_time":1.4403184,"remaining_time":0.8865287731},
{"learn":[3.688020895],"iteration":619,"passed_time":1.442009393,"remaining_time":0.8838122087},
{"learn":[3.685491894],"iteration":620,"passed_time":1.444005396,"remaining_time":0.8812850965},
{"learn":[3.684328128],"iteration":621,"passed_time":1.44565934,"remaining_time":0.8785518177},
{"learn":[3.680640153],"iteration":622,"passed_time":1.447595984,"remaining_time":0.8759930756},
{"learn":[3.678932783],"iteration":623,"passed_time":1.450895862,"remaining_time":0.8742577632},
{"learn":[3.674167041],"iteration":624,"passed_time":1.452785767,"remaining_time":0.8716714603},
{"learn":[3.672200976],"iteration":625,"passed_time":1.454641966,"remaining_time":0.8690672451},
{"learn":[3.670606604],"iteration":626,"passed_time":1.456440259,"remaining_time":0.8664309676},
{"learn":[3.665506042],"iteration":627,"passed_time":1.458218041,"remaining_time":0.8637852092},
{"learn":[3.664214007],"iteration":628,"passed_time":1.460097837,"remaining_time":0.8612023807},
{"learn":[3.66261643],"iteration":629,"passed_time":1.461870611,"remaining_time":0.85855893},
{"learn":[3.662118449],"iteration":630,"passed_time":1.464609759,"remaining_time":0.8564833616},
{"learn":[3.660871366],"iteration":631,"passed_time":1.467335065,"remaining_time":0.8543976329},
{"learn":[3.656695243],"iteration":632,"passed_time":1.46951456,"remaining_time":0.8519934337},
{"learn":[3.654497801],"iteration":633,"passed_time":1.472461531,"remaining_time":0.8500329972},
{"learn":[3.654189134],"iteration":634,"passed_time":1.474341237,"remaining_time":0.8474559868},
{"learn":[3.653957699],"iteration":635,"passed_time":1.476800655,"remaining_time":0.8452129537},
{"learn":[3.651920725],"iteration":636,"passed_time":1.481372831,"remaining_time":0.8441732146},
{"learn":[3.65106705],"iteration":637,"passed_time":1.483693264,"remaining_time":0.8418447674},
{"learn":[3.650612844],"iteration":638,"passed_time":1.48676355,"remaining_time":0.8399399711},
{"learn":[3.649884732],"iteration":639,"passed_time":1.490617498,"remaining_time":0.8384723427},
{"learn":[3.646276182],"iteration":640,"passed_time":1.494191355,"remaining_time":0.8368403998},
{"learn":[3.645808194],"iteration":641,"passed_time":1.498668368,"remaining_time":0.8357060368},
{"learn":[3.645042989],"iteration":642,"passed_time":1.502532654,"remaining_time":0.8342210848},
{"learn":[3.639864499],"iteration":643,"passed_time":1.505610575,"remaining_time":0.8322940445},
{"learn":[3.637318478],"iteration":644,"passed_time":1.508836615,"remaining_time":0.8304449586},
{"learn":[3.636344905],"iteration":645,"passed_time":1.512971334,"remaining_time":0.8290895546},
{"learn":[3.634754643],"iteration":646,"passed_time":1.517583073,"remaining_time":0.827985819},
{"learn":[3.630724975],"iteration":647,"passed_time":1.519776769,"remaining_time":0.8255577512},
{"learn":[3.629408252],"iteration":648,"passed_time":1.521846164,"remaining_time":0.8230631795},
{"learn":[3.62790646],"iteration":649,"passed_time":1.524328378,"remaining_time":0.8207922036},
{"learn":[3.627388973],"iteration":650,"passed_time":1.528084247,"remaining_time":0.819203383},
{"learn":[3.625163557],"iteration":651,"passed_time":1.530207528,"remaining_time":0.8167365331},
{"learn":[3.623701985],"iteration":652,"passed_time":1.532506269,"remaining_time":0.8143639743},
{"learn":[3.622342639],"iteration":653,"passed_time":1.534603024,"remaining_time":0.8118847804},
{"learn":[3.621130639],"iteration":654,"passed_time":1.537150872,"remaining_time":0.8096443526},
{"learn":[3.619125665],"iteration":655,"passed_time":1.541846752,"remaining_time":0.8085293944},
{"learn":[3.618878783],"iteration":656,"passed_time":1.545159205,"remaining_time":0.8066812895},
{"learn":[3.616207429],"iteration":657,"passed_time":1.547522992,"remaining_time":0.8043356585},
{"learn":[3.61206486],"iteration":658,"passed_time":1.549893246,"remaining_time":0.8019933186},
{"learn":[3.611955873],"iteration":659,"passed_time":1.551844989,"remaining_time":0.7994352976},
{"learn":[3.610713743],"iteration":660,"passed_time":1.554962804,"remaining_time":0.7974771416},
{"learn":[3.610044025],"iteration":661,"passed_time":1.558588126,"remaining_time":0.795774602},
{"learn":[3.607342669],"iteration":662,"passed_time":1.561028439,"remaining_time":0.7934639276},
{"learn":[3.602510618],"iteration":663,"passed_time":1.563112642,"remaining_time":0.7909726622},
{"learn":[3.600492392],"iteration":664,"passed_time":1.564992404,"remaining_time":0.7883796321},
{"learn":[3.597171065],"iteration":665,"passed_time":1.567108022,"remaining_time":0.7859070258},
{"learn":[3.594358798],"iteration":666,"passed_time":1.570156261,"remaining_time":0.7839011017},
{"learn":[3.593945251],"iteration":667,"passed_time":1.573181984,"remaining_time":0.7818808664},
{"learn":[3.593607748],"iteration":668,"passed_time":1.574912977,"remaining_time":0.7792170335},
{"learn":[3.592238714],"iteration":669,"passed_time":1.576905585,"remaining_time":0.7766848403},
{"learn":[3.590144654],"iteration":670,"passed_time":1.578961779,"remaining_time":0.7741854327},
{"learn":[3.587151536],"iteration":671,"passed_time":1.580712228,"remaining_time":0.7715381114},
{"learn":[3.586070865],"iteration":672,"passed_time":1.583201714,"remaining_time":0.7692525418},
{"learn":[3.585102746],"iteration":673,"passed_time":1.587070791,"remaining_time":0.7676336468},
{"learn":[3.584362847],"iteration":674,"passed_time":1.58883577,"remaining_time":0.7649950002},
{"learn":[3.581407561],"iteration":675,"passed_time":1.590640938,"remaining_time":0.7623782011},
{"learn":[3.57919422],"iteration":676,"passed_time":1.592505658,"remaining_time":0.7597922119},
{"learn":[3.577632204],"iteration":677,"passed_time":1.594644528,"remaining_time":0.7573385517},
{"learn":[3.573911195],"iteration":678,"passed_time":1.59667782,"remaining_time":0.7548359061},
{"learn":[3.573408216],"iteration":679,"passed_time":1.599370632,"remaining_time":0.7526450035},
{"learn":[3.571076482],"iteration":680,"passed_time":1.603051539,"remaining_time":0.7509154784},
{"learn":[3.568177107],"iteration":681,"passed_time":1.605266395,"remaining_time":0.7484966476},
{"learn":[3.564824621],"iteration":682,"passed_time":1.607938894,"remaining_time":0.746290819},
{"learn":[3.562475026],"iteration":683,"passed_time":1.610360203,"remaining_time":0.7439675792},
{"learn":[3.561226889],"iteration":684,"passed_time":1.612417655,"remaining_time":0.7414767317},
{"learn":[3.559383467],"iteration":685,"passed_time":1.614524444,"remaining_time":0.739009731},
{"learn":[3.555209766],"iteration":686,"passed_time":1.618194927,"remaining_time":0.7372562041},
{"learn":[3.55345383],"iteration":687,"passed_time":1.620103443,"remaining_time":0.734698073},
{"learn":[3.552300968],"iteration":688,"passed_time":1.622191327,"remaining_time":0.7322227906},
{"learn":[3.551253986],"iteration":689,"passed_time":1.624273685,"remaining_time":0.7297461484},
{"learn":[3.549807725],"iteration":690,"passed_time":1.626154287,"remaining_time":0.7271804264},
{"learn":[3.547992926],"iteration":691,"passed_time":1.628207258,"remaining_time":0.7246934037},
{"learn":[3.545438607],"iteration":692,"passed_time":1.6323883,"remaining_time":0.7231503724},
{"learn":[3.543313763],"iteration":693,"passed_time":1.634522111,"remaining_time":0.7206970691},
{"learn":[3.542962896],"iteration":694,"passed_time":1.636568802,"remaining_time":0.7182064529},
{"learn":[3.539800465],"iteration":695,"passed_time":1.638326315,"remaining_time":0.7155908043},
{"learn":[3.53953187],"iteration":696,"passed_time":1.640403523,"remaining_time":0.7131165963},
{"learn":[3.536332425],"iteration":697,"passed_time":1.642550353,"remaining_time":0.7106736486},
{"learn":[3.534993327],"iteration":698,"passed_time":1.646790045,"remaining_time":0.7091327661},
{"learn":[3.531637011],"iteration":699,"passed_time":1.649185839,"remaining_time":0.7067939308},
{"learn":[3.531040284],"iteration":700,"passed_time":1.651286656,"remaining_time":0.7043291157},
{"learn":[3.529973872],"iteration":701,"passed_time":1.653240498,"remaining_time":0.7018029466},
{"learn":[3.527325183],"iteration":702,"passed_time":1.655327859,"remaining_time":0.6993348138},
{"learn":[3.527200815],"iteration":703,"passed_time":1.657164272,"remaining_time":0.6967622506},
{"learn":[3.523459911],"iteration":704,"passed_time":1.659457798,"remaining_time":0.6943830504},
{"learn":[3.522729934],"iteration":705,"passed_time":1.663007429,"remaining_time":0.692527173},
{"learn":[3.522260582],"iteration":706,"passed_time":1.664865299,"remaining_time":0.6899653927},
{"learn":[3.518641591],"iteration":707,"passed_time":1.666847847,"remaining_time":0.6874570217},
{"learn":[3.516856405],"iteration":708,"passed_time":1.668954172,"remaining_time":0.6850009364},
{"learn":[3.515083413],"iteration":709,"passed_time":1.671319452,"remaining_time":0.6826516072},
{"learn":[3.514671214],"iteration":710,"passed_time":1.674315037,"remaining_time":0.6805584326},
{"learn":[3.512617621],"iteration":711,"passed_time":1.677679228,"remaining_time":0.6786118224},
{"learn":[3.510747971],"iteration":712,"passed_time":1.679517223,"remaining_time":0.6760469047},
{"learn":[3.508149266],"iteration":713,"passed_time":1.68124143,"remaining_time":0.6734384441},
{"learn":[3.504557165],"iteration":714,"passed_time":1.683288213,"remaining_time":0.6709610358},
{"learn":[3.501367208],"iteration":715,"passed_time":1.684986439,"remaining_time":0.6683465762},
{"learn":[3.497593362],"iteration":716,"passed_time":1.687113676,"remaining_time":0.6659040034},
{"learn":[3.496291169],"iteration":717,"passed_time":1.690341961,"remaining_time":0.6638947537},
{"learn":[3.49330374],"iteration":718,"passed_time":1.69347497,"remaining_time":0.6618448769},
{"learn":[3.490044385],"iteration":719,"passed_time":1.695757305,"remaining_time":0.6594611742},
{"learn":[3.488891789],"iteration":720,"passed_time":1.697931878,"remaining_time":0.6570360528},
{"learn":[3.486869081],"iteration":721,"passed_time":1.699755289,"remaining_time":0.6544764132},
{"learn":[3.486303638],"iteration":722,"passed_time":1.701473518,"remaining_time":0.6518785124},
{"learn":[3.486035862],"iteration":723,"passed_time":1.703781597,"remaining_time":0.6495079018},
{"learn":[3.482668951],"iteration":724,"passed_time":1.707069467,"remaining_time":0.6475091083},
{"learn":[3.47820549],"iteration":725,"passed_time":1.709133087,"remaining_time":0.6450447188},
{"learn":[3.474392283],"iteration":726,"passed_time":1.711122745,"remaining_time":0.642553658},
{"learn":[3.472268163],"iteration":727,"passed_time":1.713026219,"remaining_time":0.6400317743},
{"learn":[3.471209164],"iteration":728,"passed_time":1.714952498,"remaining_time":0.6375200643},
{"learn":[3.470049971],"iteration":729,"passed_time":1.716772202,"remaining_time":0.6349705406},
{"learn":[3.469078654],"iteration":730,"passed_time":1.719300606,"remaining_time":0.6326838071},
{"learn":[3.468643292],"iteration":731,"passed_time":1.722066892,"remaining_time":0.6304835068},
{"learn":[3.468134848],"iteration":732,"passed_time":1.723898883,"remaining_time":0.6279413393},
{"learn":[3.467820182],"iteration":733,"passed_time":1.725702513,"remaining_time":0.625390829},
{"learn":[3.465776156],"iteration":734,"passed_time":1.727453657,"remaining_time":0.6228234272},
{"learn":[3.463037608],"iteration":735,"passed_time":1.729280176,"remaining_time":0.6202852807},
{"learn":[3.45965637],"iteration":736,"passed_time":1.731120297,"remaining_time":0.6177539186},
{"learn":[3.457275091],"iteration":737,"passed_time":1.733528642,"remaining_time":0.6154261574},
{"learn":[3.455522955],"iteration":738,"passed_time":1.73588473,"remaining_time":0.6130797218},
{"learn":[3.451270508],"iteration":739,"passed_time":1.737627329,"remaining_time":0.6105177104},
{"learn":[3.450978947],"iteration":740,"passed_time":1.739438826,"remaining_time":0.6079819918},
{"learn":[3.450608492],"iteration":741,"passed_time":1.741214217,"remaining_time":0.6054356711},
{"learn":[3.448122004],"iteration":742,"passed_time":1.743006905,"remaining_time":0.6028974087},
{"learn":[3.445646714],"iteration":743,"passed_time":1.744893803,"remaining_time":0.6003935665},
{"learn":[3.44411263],"iteration":744,"passed_time":1.746589817,"remaining_time":0.5978260448},
{"learn":[3.443264164],"iteration":745,"passed_time":1.750175637,"remaining_time":0.5959043054},
{"learn":[3.439521363],"iteration":746,"passed_time":1.752494905,"remaining_time":0.5935491445},
{"learn":[3.436809225],"iteration":747,"passed_time":1.754420129,"remaining_time":0.591061327},
{"learn":[3.435509465],"iteration":748,"passed_time":1.756304829,"remaining_time":0.5885614313},
{"learn":[3.434450277],"iteration":749,"passed_time":1.758131408,"remaining_time":0.5860438026},
{"learn":[3.431786753],"iteration":750,"passed_time":1.759991117,"remaining_time":0.5835389988},
{"learn":[3.430150302],"iteration":751,"passed_time":1.762075366,"remaining_time":0.5811099611},
{"learn":[3.42696281],"iteration":752,"passed_time":1.765972534,"remaining_time":0.579276515},
{"learn":[3.426870334],"iteration":753,"passed_time":1.767942355,"remaining_time":0.5768087791},
{"learn":[3.425200309],"iteration":754,"passed_time":1.77004689,"remaining_time":0.5743860769},
{"learn":[3.423383783],"iteration":755,"passed_time":1.771829912,"remaining_time":0.5718604477},
{"learn":[3.422752979],"iteration":756,"passed_time":1.773611622,"remaining_time":0.5693363595},
{"learn":[3.420845924],"iteration":757,"passed_time":1.775590804,"remaining_time":0.5668772751},
{"learn":[3.418917862],"iteration":758,"passed_time":1.778113624,"remaining_time":0.5645920729},
{"learn":[3.417095735],"iteration":759,"passed_time":1.781688655,"remaining_time":0.5626385226},
{"learn":[3.414391848],"iteration":760,"passed_time":1.783784757,"remaining_time":0.5602162376},
{"learn":[3.41426711],"iteration":761,"passed_time":1.785581945,"remaining_time":0.5577014473},
{"learn":[3.411976013],"iteration":762,"passed_time":1.787371378,"remaining_time":0.5551861293},
{"learn":[3.408614844],"iteration":763,"passed_time":1.789350533,"remaining_time":0.5527313166},
{"learn":[3.407906721],"iteration":764,"passed_time":1.791428086,"remaining_time":0.550307974},
{"learn":[3.407494015],"iteration":765,"passed_time":1.794120427,"remaining_time":0.548073342},
{"learn":[3.406287128],"iteration":766,"passed_time":1.797667934,"remaining_time":0.5460972992},
{"learn":[3.404600442],"iteration":767,"passed_time":1.800244399,"remaining_time":0.543823829},
{"learn":[3.404012662],"iteration":768,"passed_time":1.802976783,"remaining_time":0.5415964069},
{"learn":[3.400398762],"iteration":769,"passed_time":1.805120759,"remaining_time":0.5391919149},
{"learn":[3.399737714],"iteration":770,"passed_time":1.80834325,"remaining_time":0.5371084361},
{"learn":[3.399185251],"iteration":771,"passed_time":1.811456258,"remaining_time":0.534989672},
{"learn":[3.397245411],"iteration":772,"passed_time":1.814518181,"remaining_time":0.5328533338},
{"learn":[3.396229831],"iteration":773,"passed_time":1.816321005,"remaining_time":0.5303469603},
{"learn":[3.394002836],"iteration":774,"passed_time":1.819145522,"remaining_time":0.5281390225},
{"learn":[3.389617243],"iteration":775,"passed_time":1.821497022,"remaining_time":0.5257929549},
{"learn":[3.385426488],"iteration":776,"passed_time":1.824421271,"remaining_time":0.5236112527},
{"learn":[3.385072258],"iteration":777,"passed_time":1.828288515,"remaining_time":0.5216967228},
{"learn":[3.383842366],"iteration":778,"passed_time":1.831200459,"remaining_time":0.5195061636},
{"learn":[3.380110746],"iteration":779,"passed_time":1.833551797,"remaining_time":0.5171556349},
{"learn":[3.378595218],"iteration":780,"passed_time":1.83555762,"remaining_time":0.5147082187},
{"learn":[3.377371219],"iteration":781,"passed_time":1.837795075,"remaining_time":0.5123265044},
{"learn":[3.375814782],"iteration":782,"passed_time":1.842825016,"remaining_time":0.5107190657},
{"learn":[3.374195887],"iteration":783,"passed_time":1.844940977,"remaining_time":0.508300065},
{"learn":[3.373704309],"iteration":784,"passed_time":1.847943884,"remaining_time":0.506124758},
{"learn":[3.372971757],"iteration":785,"passed_time":1.85001172,"remaining_time":0.5036927583},
{"learn":[3.371565136],"iteration":786,"passed_time":1.851929916,"remaining_time":0.5012211844},
{"learn":[3.3700309],"iteration":787,"passed_time":1.854979756,"remaining_time":0.4990554672},
{"learn":[3.368186663],"iteration":788,"passed_time":1.857968344,"remaining_time":0.4968711287},
{"learn":[3.366710398],"iteration":789,"passed_time":1.860505809,"remaining_time":0.4945648352},
{"learn":[3.364598042],"iteration":790,"passed_time":1.862840286,"remaining_time":0.4922043234},
{"learn":[3.36348442],"iteration":791,"passed_time":1.865761631,"remaining_time":0.4899980041},
{"learn":[3.362001759],"iteration":792,"passed_time":1.869245423,"remaining_time":0.4879366993},
{"learn":[3.361580401],"iteration":793,"passed_time":1.873253105,"remaining_time":0.4860077325},
{"learn":[3.359543675],"iteration":794,"passed_time":1.875138476,"remaining_time":0.4835262738},
{"learn":[3.35766119],"iteration":795,"passed_time":1.87735934,"remaining_time":0.4811322932},
{"learn":[3.354592969],"iteration":796,"passed_time":1.88008532,"remaining_time":0.4788674027},
{"learn":[3.350985986],"iteration":797,"passed_time":1.884221277,"remaining_time":0.476958268},
{"learn":[3.349589624],"iteration":798,"passed_time":1.890215937,"remaining_time":0.475511143},
{"learn":[3.349110856],"iteration":799,"passed_time":1.894860992,"remaining_time":0.4737152479},
{"learn":[3.345315441],"iteration":800,"passed_time":1.896974319,"remaining_time":0.4712832577},
{"learn":[3.34397474],"iteration":801,"passed_time":1.899746256,"remaining_time":0.4690146617},
{"learn":[3.343800902],"iteration":802,"passed_time":1.902658824,"remaining_time":0.4667793129},
{"learn":[3.342329465],"iteration":803,"passed_time":1.904912083,"remaining_time":0.4643815527},
{"learn":[3.34220347],"iteration":804,"passed_time":1.906746311,"remaining_time":0.4618826467},
{"learn":[3.341279219],"iteration":805,"passed_time":1.908723655,"remaining_time":0.4594198375},
{"learn":[3.337329521],"iteration":806,"passed_time":1.910693534,"remaining_time":0.4569564461},
{"learn":[3.336708453],"iteration":807,"passed_time":1.913165736,"remaining_time":0.4546136402},
{"learn":[3.333252703],"iteration":808,"passed_time":1.917976592,"remaining_time":0.4528226563},
{"learn":[3.332186769],"iteration":809,"passed_time":1.920476627,"remaining_time":0.4504821718},
{"learn":[3.330594851],"iteration":810,"passed_time":1.922509347,"remaining_time":0.4480323879},
{"learn":[3.327867442],"iteration":811,"passed_time":1.924335817,"remaining_time":0.4455358787},
{"learn":[3.327563111],"iteration":812,"passed_time":1.926214868,"remaining_time":0.4430531122},
{"learn":[3.326308994],"iteration":813,"passed_time":1.928460444,"remaining_time":0.4406555807},
{"learn":[3.326249879],"iteration":814,"passed_time":1.930894436,"remaining_time":0.438301191},
{"learn":[3.322336238],"iteration":815,"passed_time":1.933527583,"remaining_time":0.4359915138},
{"learn":[3.320491154],"iteration":816,"passed_time":1.936466919,"remaining_time":0.4337496282},
{"learn":[3.320434271],"iteration":817,"passed_time":1.93930324,"remaining_time":0.4314831169},
{"learn":[3.319609638],"iteration":818,"passed_time":1.942144464,"remaining_time":0.4292162979},
{"learn":[3.316182682],"iteration":819,"passed_time":1.946549642,"remaining_time":0.4272913848},
{"learn":[3.313126612],"iteration":820,"passed_time":1.950203602,"remaining_time":0.425196644},
{"learn":[3.311222803],"iteration":821,"passed_time":1.952393588,"remaining_time":0.4227810933},
{"learn":[3.309627335],"iteration":822,"passed_time":1.954739636,"remaining_time":0.4203996545},
{"learn":[3.307974895],"iteration":823,"passed_time":1.957501538,"remaining_time":0.4181071246},
{"learn":[3.307321505],"iteration":824,"passed_time":1.962271522,"remaining_time":0.4162394137},
{"learn":[3.306759087],"iteration":825,"passed_time":1.965271613,"remaining_time":0.4139918409},
{"learn":[3.30484037],"iteration":826,"passed_time":1.967270107,"remaining_time":0.4115329244},
{"learn":[3.30201994],"iteration":827,"passed_time":1.968990551,"remaining_time":0.4090173608},
{"learn":[3.299302297],"iteration":828,"passed_time":1.970835242,"remaining_time":0.4065293443},
{"learn":[3.298132671],"iteration":829,"passed_time":1.973190828,"remaining_time":0.4041475189},
{"learn":[3.296976183],"iteration":830,"passed_time":1.977035225,"remaining_time":0.4020685356},
{"learn":[3.293144745],"iteration":831,"passed_time":1.979159184,"remaining_time":0.3996379121},
{"learn":[3.290284404],"iteration":832,"passed_time":1.981624788,"remaining_time":0.3972765182},
{"learn":[3.288285745],"iteration":833,"passed_time":1.983651984,"remaining_time":0.3948276132},
{"learn":[3.286662667],"iteration":834,"passed_time":1.985518489,"remaining_time":0.392347965},
{"learn":[3.285692682],"iteration":835,"passed_time":1.987788593,"remaining_time":0.3899489585},
{"learn":[3.284565611],"iteration":836,"passed_time":1.991220505,"remaining_time":0.387776514},
{"learn":[3.283897383],"iteration":837,"passed_time":1.994322064,"remaining_time":0.385537201},
{"learn":[3.280712855],"iteration":838,"passed_time":1.997340369,"remaining_time":0.3832798562},
{"learn":[3.280468341],"iteration":839,"passed_time":1.999362566,"remaining_time":0.380830965},
{"learn":[3.277814895],"iteration":840,"passed_time":2.001755831,"remaining_time":0.3784532427},
{"learn":[3.276316385],"iteration":841,"passed_time":2.005050503,"remaining_time":0.3762446312},
{"learn":[3.27557063],"iteration":842,"passed_time":2.008689999,"remaining_time":0.3740976629},
{"learn":[3.27499628],"iteration":843,"passed_time":2.010524831,"remaining_time":0.3716135943},
{"learn":[3.273569958],"iteration":844,"passed_time":2.012541872,"remaining_time":0.3691644854},
{"learn":[3.269665595],"iteration":845,"passed_time":2.014344663,"remaining_time":0.3666773974},
{"learn":[3.267984685],"iteration":846,"passed_time":2.016219823,"remaining_time":0.3642049975},
{"learn":[3.267702508],"iteration":847,"passed_time":2.019589061,"remaining_time":0.3620018127},
{"learn":[3.266671924],"iteration":848,"passed_time":2.023188858,"remaining_time":0.3598368876},
{"learn":[3.265359825],"iteration":849,"passed_time":2.025626597,"remaining_time":0.3574635171},
{"learn":[3.2618983],"iteration":850,"passed_time":2.027688011,"remaining_time":0.3550241054},
{"learn":[3.260456253],"iteration":851,"passed_time":2.029662253,"remaining_time":0.3525704383},
{"learn":[3.258389147],"iteration":852,"passed_time":2.031569148,"remaining_time":0.3501062892},
{"learn":[3.258108469],"iteration":853,"passed_time":2.033752053,"remaining_time":0.347690632},
{"learn":[3.256424936],"iteration":854,"passed_time":2.037215967,"remaining_time":0.3454927663},
{"learn":[3.254817983],"iteration":855,"passed_time":2.039264962,"remaining_time":0.3430539189},
{"learn":[3.253898449],"iteration":856,"passed_time":2.041073209,"remaining_time":0.3405758097},
{"learn":[3.253023652],"iteration":857,"passed_time":2.042956125,"remaining_time":0.3381116198},
{"learn":[3.252845542],"iteration":858,"passed_time":2.04494246,"remaining_time":0.3356657588},
{"learn":[3.252316026],"iteration":859,"passed_time":2.047025323,"remaining_time":0.3332366804},
{"learn":[3.24975301],"iteration":860,"passed_time":2.049137081,"remaining_time":0.3308130711},
{"learn":[3.249151075],"iteration":861,"passed_time":2.053103541,"remaining_time":0.3286871099},
{"learn":[3.246257135],"iteration":862,"passed_time":2.054777871,"remaining_time":0.3261930108},
{"learn":[3.243826471],"iteration":863,"passed_time":2.056562229,"remaining_time":0.3237181286},
{"learn":[3.243190653],"iteration":864,"passed_time":2.058523678,"remaining_time":0.3212724815},
{"learn":[3.24008797],"iteration":865,"passed_time":2.060439187,"remaining_time":0.3188208442},
{"learn":[3.240036811],"iteration":866,"passed_time":2.062590741,"remaining_time":0.3164066535},
{"learn":[3.238676314],"iteration":867,"passed_time":2.065708427,"remaining_time":0.3141399912},
{"learn":[3.237848782],"iteration":868,"passed_time":2.068557649,"remaining_time":0.3118308999},
{"learn":[3.236405498],"iteration":869,"passed_time":2.070409869,"remaining_time":0.3093715896},
{"learn":[3.233378068],"iteration":870,"passed_time":2.072075271,"remaining_time":0.3068860045},
{"learn":[3.233169169],"iteration":871,"passed_time":2.073951923,"remaining_time":0.3044333098},
{"learn":[3.232434885],"iteration":872,"passed_time":2.075676742,"remaining_time":0.3019598468},
{"learn":[3.229978115],"iteration":873,"passed_time":2.07784091,"remaining_time":0.2995514356},
{"learn":[3.229648848],"iteration":874,"passed_time":2.08062736,"remaining_time":0.29723248},
{"learn":[3.227208761],"iteration":875,"passed_time":2.084182881,"remaining_time":0.295021321},
{"learn":[3.226258869],"iteration":876,"passed_time":2.08648938,"remaining_time":0.2926319199},
{"learn":[3.225331995],"iteration":877,"passed_time":2.088779573,"remaining_time":0.2902404419},
{"learn":[3.221968268],"iteration":878,"passed_time":2.090724336,"remaining_time":0.2878016435},
{"learn":[3.221166317],"iteration":879,"passed_time":2.092660863,"remaining_time":0.285362845},
{"learn":[3.220047503],"iteration":880,"passed_time":2.095280054,"remaining_time":0.2830173966},
{"learn":[3.21982781],"iteration":881,"passed_time":2.098174584,"remaining_time":0.2807081643},
{"learn":[3.216693405],"iteration":882,"passed_time":2.100067587,"remaining_time":0.2782649012},
{"learn":[3.214798761],"iteration":883,"passed_time":2.102243783,"remaining_time":0.2758600439},
{"learn":[3.214395085],"iteration":884,"passed_time":2.104046944,"remaining_time":0.27340723},
{"learn":[3.213470696],"iteration":885,"passed_time":2.105784228,"remaining_time":0.2709474064},
{"learn":[3.211595017],"iteration":886,"passed_time":2.107517939,"remaining_time":0.2684887567},
{"learn":[3.210965255],"iteration":887,"passed_time":2.110167436,"remaining_time":0.2661472442},
{"learn":[3.209413583],"iteration":888,"passed_time":2.113331181,"remaining_time":0.2638692476},
{"learn":[3.208331683],"iteration":889,"passed_time":2.11589636,"remaining_time":0.2615152805},
{"learn":[3.207110711],"iteration":890,"passed_time":2.118178948,"remaining_time":0.2591262686},
{"learn":[3.204519413],"iteration":891,"passed_time":2.120233052,"remaining_time":0.2567098314},
{"learn":[3.201421296],"iteration":892,"passed_time":2.122209586,"remaining_time":0.2542849112},
{"learn":[3.200691259],"iteration":893,"passed_time":2.124579963,"remaining_time":0.2519076914},
{"learn":[3.200485067],"iteration":894,"passed_time":2.128563028,"remaining_time":0.2497196849},
{"learn":[3.197467568],"iteration":895,"passed_time":2.136399538,"remaining_time":0.2479749464},
{"learn":[3.195838544],"iteration":896,"passed_time":2.140423393,"remaining_time":0.2457788288},
{"learn":[3.195671746],"iteration":897,"passed_time":2.143135353,"remaining_time":0.2434296281},
{"learn":[3.194213094],"iteration":898,"passed_time":2.146786733,"remaining_time":0.2411851614},
{"learn":[3.192884691],"iteration":899,"passed_time":2.149009715,"remaining_time":0.2387788572},
{"learn":[3.188364239],"iteration":900,"passed_time":2.150924078,"remaining_time":0.2363390497},
{"learn":[3.185219478],"iteration":901,"passed_time":2.154259845,"remaining_time":0.234054839},
{"learn":[3.184120387],"iteration":902,"passed_time":2.157497655,"remaining_time":0.2317577769},
{"learn":[3.183725321],"iteration":903,"passed_time":2.160274996,"remaining_time":0.2294097341},
{"learn":[3.181264554],"iteration":904,"passed_time":2.162436637,"remaining_time":0.2269961111},
{"learn":[3.180741589],"iteration":905,"passed_time":2.164402304,"remaining_time":0.2245627114},
{"learn":[3.179782639],"iteration":906,"passed_time":2.16665422,"remaining_time":0.222159694},
{"learn":[3.176377564],"iteration":907,"passed_time":2.169041435,"remaining_time":0.2197707181},
{"learn":[3.174078182],"iteration":908,"passed_time":2.173201732,"remaining_time":0.2175592493},
{"learn":[3.171242379],"iteration":909,"passed_time":2.175357405,"remaining_time":0.2151452378},
{"learn":[3.170421012],"iteration":910,"passed_time":2.177374887,"remaining_time":0.212718293},
{"learn":[3.170087224],"iteration":911,"passed_time":2.179471045,"remaining_time":0.2102998377},
{"learn":[3.167303059],"iteration":912,"passed_time":2.181488329,"remaining_time":0.2078745724},
{"learn":[3.16705966],"iteration":913,"passed_time":2.183784801,"remaining_time":0.2054764692},
{"learn":[3.165667683],"iteration":914,"passed_time":2.187473531,"remaining_time":0.2032079236},
{"learn":[3.164689733],"iteration":915,"passed_time":2.190043871,"remaining_time":0.2008337174},
{"learn":[3.163311455],"iteration":916,"passed_time":2.192355958,"remaining_time":0.1984357083},
{"learn":[3.159425016],"iteration":917,"passed_time":2.194477805,"remaining_time":0.1960208933},
{"learn":[3.159327058],"iteration":918,"passed_time":2.19753509,"remaining_time":0.1936891647},
{"learn":[3.15819426],"iteration":919,"passed_time":2.200972006,"remaining_time":0.1913888701},
{"learn":[3.157086603],"iteration":920,"passed_time":2.203866314,"remaining_time":0.1890395644},
{"learn":[3.153354154],"iteration":921,"passed_time":2.205981724,"remaining_time":0.1866231827},
{"learn":[3.153261317],"iteration":922,"passed_time":2.207768035,"remaining_time":0.1841799986},
{"learn":[3.153168454],"iteration":923,"passed_time":2.209711644,"remaining_time":0.1817511742},
{"learn":[3.152080399],"iteration":924,"passed_time":2.211629639,"remaining_time":0.1793213221},
{"learn":[3.151635144],"iteration":925,"passed_time":2.214408928,"remaining_time":0.1769614046},
{"learn":[3.147762655],"iteration":926,"passed_time":2.217469658,"remaining_time":0.1746227454},
{"learn":[3.147172317],"iteration":927,"passed_time":2.219888241,"remaining_time":0.1722327083},
{"learn":[3.146254125],"iteration":928,"passed_time":2.221892291,"remaining_time":0.1698109286},
{"learn":[3.144869828],"iteration":929,"passed_time":2.224107738,"remaining_time":0.1674059588},
{"learn":[3.143466218],"iteration":930,"passed_time":2.227773527,"remaining_time":0.1651088865},
{"learn":[3.141919643],"iteration":931,"passed_time":2.232370483,"remaining_time":0.1628768163},
{"learn":[3.141054135],"iteration":932,"passed_time":2.235755947,"remaining_time":0.1605526778},
{"learn":[3.139390417],"iteration":933,"passed_time":2.239776871,"remaining_time":0.1582711708},
{"learn":[3.139025283],"iteration":934,"passed_time":2.243410541,"remaining_time":0.1559590216},
{"learn":[3.137824183],"iteration":935,"passed_time":2.249566965,"remaining_time":0.1538165446},
{"learn":[3.135620453],"iteration":936,"passed_time":2.252326098,"remaining_time":0.1514370802},
{"learn":[3.13443178],"iteration":937,"passed_time":2.255233788,"remaining_time":0.1490666257},
{"learn":[3.132765713],"iteration":938,"passed_time":2.260101405,"remaining_time":0.146822349},
{"learn":[3.131434124],"iteration":939,"passed_time":2.265143176,"remaining_time":0.144583607},
{"learn":[3.128384262],"iteration":940,"passed_time":2.267527995,"remaining_time":0.1421723185},
{"learn":[3.128120455],"iteration":941,"passed_time":2.26996382,"remaining_time":0.1397642267},
{"learn":[3.126314615],"iteration":942,"passed_time":2.27236923,"remaining_time":0.1373542376},
{"learn":[3.125409666],"iteration":943,"passed_time":2.275338894,"remaining_time":0.134977731},
{"learn":[3.123072589],"iteration":944,"passed_time":2.278248857,"remaining_time":0.1325964943},
{"learn":[3.122921099],"iteration":945,"passed_time":2.280291319,"remaining_time":0.1301646208},
{"learn":[3.122182662],"iteration":946,"passed_time":2.282285906,"remaining_time":0.1277308902},
{"learn":[3.120040951],"iteration":947,"passed_time":2.284480834,"remaining_time":0.1253090753},
{"learn":[3.118767799],"iteration":948,"passed_time":2.287281033,"remaining_time":0.1229202663},
{"learn":[3.118203218],"iteration":949,"passed_time":2.290805948,"remaining_time":0.1205687341},
{"learn":[3.116343362],"iteration":950,"passed_time":2.294239868,"remaining_time":0.1182100458},
{"learn":[3.11480829],"iteration":951,"passed_time":2.296426216,"remaining_time":0.1157861958},
{"learn":[3.112607903],"iteration":952,"passed_time":2.298896472,"remaining_time":0.113376846},
{"learn":[3.111661241],"iteration":953,"passed_time":2.301263698,"remaining_time":0.1109624005},
{"learn":[3.110249676],"iteration":954,"passed_time":2.305655593,"remaining_time":0.1086434573},
{"learn":[3.107333579],"iteration":955,"passed_time":2.309851155,"remaining_time":0.106311141},
{"learn":[3.107149851],"iteration":956,"passed_time":2.312072169,"remaining_time":0.1038862103},
{"learn":[3.106867336],"iteration":957,"passed_time":2.314426571,"remaining_time":0.1014675532},
{"learn":[3.10364681],"iteration":958,"passed_time":2.316946513,"remaining_time":0.09905610745},
{"learn":[3.102703811],"iteration":959,"passed_time":2.320178982,"remaining_time":0.09667412425},
{"learn":[3.101469264],"iteration":960,"passed_time":2.323754239,"remaining_time":0.09430428233},
{"learn":[3.09863569],"iteration":961,"passed_time":2.327562312,"remaining_time":0.09194113084},
{"learn":[3.09645939],"iteration":962,"passed_time":2.331712473,"remaining_time":0.089588122},
{"learn":[3.096240186],"iteration":963,"passed_time":2.335160081,"remaining_time":0.08720514826},
{"learn":[3.094838828],"iteration":964,"passed_time":2.337830099,"remaining_time":0.08479176525},
{"learn":[3.094176802],"iteration":965,"passed_time":2.340469474,"remaining_time":0.08237677236},
{"learn":[3.093182279],"iteration":966,"passed_time":2.34291861,"remaining_time":0.0799548233},
{"learn":[3.090150687],"iteration":967,"passed_time":2.344623644,"remaining_time":0.07750821965},
{"learn":[3.088612829],"iteration":968,"passed_time":2.346757267,"remaining_time":0.07507685787},
{"learn":[3.087153684],"iteration":969,"passed_time":2.349531074,"remaining_time":0.07266590951},
{"learn":[3.085866843],"iteration":970,"passed_time":2.352385134,"remaining_time":0.07025661059},
{"learn":[3.082669094],"iteration":971,"passed_time":2.354301724,"remaining_time":0.06781939122},
{"learn":[3.081047548],"iteration":972,"passed_time":2.356389092,"remaining_time":0.06538798097},
{"learn":[3.079684322],"iteration":973,"passed_time":2.358401428,"remaining_time":0.06295527426},
{"learn":[3.07613431],"iteration":974,"passed_time":2.360438447,"remaining_time":0.06052406274},
{"learn":[3.074005935],"iteration":975,"passed_time":2.365095784,"remaining_time":0.05815809304},
{"learn":[3.072988853],"iteration":976,"passed_time":2.368205722,"remaining_time":0.05575100472},
{"learn":[3.072344268],"iteration":977,"passed_time":2.370902663,"remaining_time":0.05333318873},
{"learn":[3.070654438],"iteration":978,"passed_time":2.373607458,"remaining_time":0.05091497101},
{"learn":[3.069724506],"iteration":979,"passed_time":2.375482492,"remaining_time":0.04847923454},
{"learn":[3.067763166],"iteration":980,"passed_time":2.377875656,"remaining_time":0.04605467631},
{"learn":[3.066737893],"iteration":981,"passed_time":2.381629432,"remaining_time":0.04365512197},
{"learn":[3.065248174],"iteration":982,"passed_time":2.384295697,"remaining_time":0.04123400494},
{"learn":[3.063186837],"iteration":983,"passed_time":2.386523703,"remaining_time":0.03880526346},
{"learn":[3.062880371],"iteration":984,"passed_time":2.388363274,"remaining_time":0.03637101433},
{"learn":[3.061288645],"iteration":985,"passed_time":2.390257886,"remaining_time":0.03393875294},
{"learn":[3.059970575],"iteration":986,"passed_time":2.392392921,"remaining_time":0.03151074769},
{"learn":[3.059576341],"iteration":987,"passed_time":2.396037872,"remaining_time":0.02910167456},
{"learn":[3.058175919],"iteration":988,"passed_time":2.398930698,"remaining_time":0.02668173678},
{"learn":[3.056830702],"iteration":989,"passed_time":2.401210361,"remaining_time":0.02425465012},
{"learn":[3.056336579],"iteration":990,"passed_time":2.403128055,"remaining_time":0.02182457365},
{"learn":[3.055810414],"iteration":991,"passed_time":2.404885752,"remaining_time":0.01939423994},
{"learn":[3.055476518],"iteration":992,"passed_time":2.406813878,"remaining_time":0.01696646238},
{"learn":[3.053331734],"iteration":993,"passed_time":2.410126123,"remaining_time":0.01454804501},
{"learn":[3.050890374],"iteration":994,"passed_time":2.412716674,"remaining_time":0.01212420439},
{"learn":[3.04972623],"iteration":995,"passed_time":2.414607801,"remaining_time":0.009697220086},
{"learn":[3.047217327],"iteration":996,"passed_time":2.41646054,"remaining_time":0.007271195205},
{"learn":[3.047155483],"iteration":997,"passed_time":2.418345429,"remaining_time":0.004846383626},
{"learn":[3.04430671],"iteration":998,"passed_time":2.420165609,"remaining_time":0.002422588197},
{"learn":[3.042664195],"iteration":999,"passed_time":2.422735352,"remaining_time":0}
]}